{
  "conv_id": 1066,
  "speaker": "seeker",
  "granularity": "sentence",
  "smooth_mode": "context",
  "window_size": 2,
  "dims": {
    "valence": {
      "is_sent": true,
      "turn_to_x": {
        "1": 2.5,
        "2": 10.5,
        "4": 25.0,
        "5": 39.0,
        "8": 63.5,
        "9": 96.5,
        "12": 112.0,
        "13": 122.5,
        "17": 140.0,
        "19": 163.5,
        "22": 186.5,
        "24": 209.5,
        "26": 231.0,
        "29": 245.0,
        "30": 253.0,
        "33": 265.5,
        "35": 281.0,
        "37": 291.0,
        "38": 300.0,
        "40": 306.0,
        "43": 312.0,
        "45": 319.5,
        "46": 325.0
      },
      "seeker_curve": {
        "x": [
          0.0,
          6.0,
          16.0,
          35.0,
          44.0,
          84.0,
          110.0,
          115.0,
          131.0,
          150.0,
          178.0,
          196.0,
          224.0,
          239.0,
          252.0,
          255.0,
          277.0,
          286.0,
          297.0,
          304.0,
          309.0,
          316.0,
          324.0
        ],
        "y": [
          0.1303189992904663,
          -0.5565952062606812,
          -0.4373507499694824,
          -0.2778496742248535,
          -0.23896455764770508,
          -0.581514835357666,
          0.192604660987854,
          0.18888235092163086,
          -0.20118427276611328,
          0.07075643539428711,
          -0.1799328327178955,
          -0.04718518257141113,
          0.35355496406555176,
          -0.16029858589172363,
          0.050653696060180664,
          -0.06476199626922607,
          0.44395172595977783,
          0.21216249465942383,
          0.39040184020996094,
          -0.02626800537109375,
          0.2608451843261719,
          0.4054297208786011,
          0.40917229652404785
        ],
        "turns": [
          1,
          2,
          4,
          5,
          8,
          9,
          12,
          13,
          17,
          19,
          22,
          24,
          26,
          29,
          30,
          33,
          35,
          37,
          38,
          40,
          43,
          45,
          46
        ]
      },
      "prev": {
        "x": [
          10.5,
          25.0,
          39.0,
          63.5,
          96.5,
          112.0,
          122.5,
          140.0,
          163.5,
          186.5,
          209.5,
          231.0,
          245.0,
          253.0,
          265.5,
          281.0,
          291.0,
          300.0,
          306.0,
          312.0,
          319.5,
          325.0
        ],
        "y": [
          -0.5803312063217163,
          -0.5170181393623352,
          -0.4040732979774475,
          0.020443439483642578,
          -0.18656599521636963,
          -0.4379976987838745,
          0.25510168075561523,
          -0.16457557678222656,
          -0.2985039949417114,
          -0.16367340087890625,
          -0.3003067970275879,
          0.03232860565185547,
          0.46431398391723633,
          0.07762336730957031,
          0.2511739730834961,
          -0.5379452705383301,
          0.16574597358703613,
          0.10864949226379395,
          -0.20382297039031982,
          -0.41151177883148193,
          -0.31336164474487305,
          -0.09525871276855469
        ],
        "turns": [
          2,
          4,
          5,
          8,
          9,
          12,
          13,
          17,
          19,
          22,
          24,
          26,
          29,
          30,
          33,
          35,
          37,
          38,
          40,
          43,
          45,
          46
        ],
        "hover": [
          "T[2] ΔV=-0.580<br>上次supporter: Question<br>supporter段: T[0~0]",
          "T[4] ΔV=-0.517<br>上次supporter: Restatement or Paraphrasing<br>supporter段: T[3~3]",
          "T[5] ΔV=-0.404<br>上次supporter: Restatement or Paraphrasing<br>supporter段: T[3~3]",
          "T[8] ΔV=0.020<br>上次supporter: Affirmation and Reassurance, Providing Suggestions<br>supporter段: T[6~7]",
          "T[9] ΔV=-0.187<br>上次supporter: Affirmation and Reassurance, Providing Suggestions<br>supporter段: T[6~7]",
          "T[12] ΔV=-0.438<br>上次supporter: Affirmation and Reassurance, Information<br>supporter段: T[10~11]",
          "T[13] ΔV=0.255<br>上次supporter: Affirmation and Reassurance, Information<br>supporter段: T[10~11]",
          "T[17] ΔV=-0.165<br>上次supporter: Affirmation and Reassurance, Restatement or Paraphrasing, Question<br>supporter段: T[14~16]",
          "T[19] ΔV=-0.299<br>上次supporter: Restatement or Paraphrasing<br>supporter段: T[18~18]",
          "T[22] ΔV=-0.164<br>上次supporter: Reflection of feelings, Restatement or Paraphrasing<br>supporter段: T[20~21]",
          "T[24] ΔV=-0.300<br>上次supporter: Providing Suggestions<br>supporter段: T[23~23]",
          "T[26] ΔV=0.032<br>上次supporter: Affirmation and Reassurance<br>supporter段: T[25~25]",
          "T[29] ΔV=0.464<br>上次supporter: Others, Reflection of feelings<br>supporter段: T[27~28]",
          "T[30] ΔV=0.078<br>上次supporter: Others, Reflection of feelings<br>supporter段: T[27~28]",
          "T[33] ΔV=0.251<br>上次supporter: Self-disclosure<br>supporter段: T[31~32]",
          "T[35] ΔV=-0.538<br>上次supporter: Restatement or Paraphrasing<br>supporter段: T[34~34]",
          "T[37] ΔV=0.166<br>上次supporter: Affirmation and Reassurance<br>supporter段: T[36~36]",
          "T[38] ΔV=0.109<br>上次supporter: Affirmation and Reassurance<br>supporter段: T[36~36]",
          "T[40] ΔV=-0.204<br>上次supporter: Others<br>supporter段: T[39~39]",
          "T[43] ΔV=-0.412<br>上次supporter: Providing Suggestions, Others<br>supporter段: T[41~42]",
          "T[45] ΔV=-0.313<br>上次supporter: Others<br>supporter段: T[44~44]",
          "T[46] ΔV=-0.095<br>上次supporter: Others<br>supporter段: T[44~44]"
        ],
        "strategies": [
          [
            "Question"
          ],
          [
            "Restatement or Paraphrasing"
          ],
          [
            "Restatement or Paraphrasing"
          ],
          [
            "Affirmation and Reassurance",
            "Providing Suggestions"
          ],
          [
            "Affirmation and Reassurance",
            "Providing Suggestions"
          ],
          [
            "Affirmation and Reassurance",
            "Information"
          ],
          [
            "Affirmation and Reassurance",
            "Information"
          ],
          [
            "Affirmation and Reassurance",
            "Restatement or Paraphrasing",
            "Question"
          ],
          [
            "Restatement or Paraphrasing"
          ],
          [
            "Reflection of feelings",
            "Restatement or Paraphrasing"
          ],
          [
            "Providing Suggestions"
          ],
          [
            "Affirmation and Reassurance"
          ],
          [
            "Others",
            "Reflection of feelings"
          ],
          [
            "Others",
            "Reflection of feelings"
          ],
          [
            "Self-disclosure",
            "Self-disclosure"
          ],
          [
            "Restatement or Paraphrasing"
          ],
          [
            "Affirmation and Reassurance"
          ],
          [
            "Affirmation and Reassurance"
          ],
          [
            "Others"
          ],
          [
            "Providing Suggestions",
            "Others"
          ],
          [
            "Others"
          ],
          [
            "Others"
          ]
        ],
        "strategy_summary": [
          "Question",
          "Restatement or Paraphrasing",
          "Restatement or Paraphrasing",
          "Affirmation and Reassurance, Providing Suggestions",
          "Affirmation and Reassurance, Providing Suggestions",
          "Affirmation and Reassurance, Information",
          "Affirmation and Reassurance, Information",
          "Affirmation and Reassurance, Restatement or Paraphrasing, Question",
          "Restatement or Paraphrasing",
          "Reflection of feelings, Restatement or Paraphrasing",
          "Providing Suggestions",
          "Affirmation and Reassurance",
          "Others, Reflection of feelings",
          "Others, Reflection of feelings",
          "Self-disclosure",
          "Restatement or Paraphrasing",
          "Affirmation and Reassurance",
          "Affirmation and Reassurance",
          "Others",
          "Providing Suggestions, Others",
          "Others",
          "Others"
        ]
      },
      "next": {
        "x": [
          10.5,
          25.0,
          39.0,
          63.5,
          96.5,
          112.0,
          122.5,
          140.0,
          163.5,
          186.5,
          209.5,
          231.0,
          245.0,
          253.0,
          265.5,
          281.0,
          291.0,
          300.0,
          306.0,
          312.0,
          319.5,
          325.0
        ],
        "y": [
          -0.07194876670837402,
          -0.34308892488479614,
          -0.23014408349990845,
          -0.20872783660888672,
          -0.4157372713088989,
          -0.5654772520065308,
          0.12762212753295898,
          -0.28736042976379395,
          -0.24541723728179932,
          -0.2561492919921875,
          -0.17499876022338867,
          0.33104968070983887,
          0.5594854354858398,
          0.17279481887817383,
          -0.7392621040344238,
          -0.10929012298583984,
          -0.15597105026245117,
          -0.21306753158569336,
          -0.29340970516204834,
          -0.3616853952407837,
          -0.2899630069732666,
          -0.07186007499694824
        ],
        "turns": [
          2,
          4,
          5,
          8,
          9,
          12,
          13,
          17,
          19,
          22,
          24,
          26,
          29,
          30,
          33,
          35,
          37,
          38,
          40,
          43,
          45,
          46
        ],
        "hover": [
          "T[2] ΔV=-0.072<br>下次supporter: Restatement or Paraphrasing<br>supporter段: T[3~3]",
          "T[4] ΔV=-0.343<br>下次supporter: Affirmation and Reassurance, Providing Suggestions<br>supporter段: T[6~7]",
          "T[5] ΔV=-0.230<br>下次supporter: Affirmation and Reassurance, Providing Suggestions<br>supporter段: T[6~7]",
          "T[8] ΔV=-0.209<br>下次supporter: Affirmation and Reassurance, Information<br>supporter段: T[10~11]",
          "T[9] ΔV=-0.416<br>下次supporter: Affirmation and Reassurance, Information<br>supporter段: T[10~11]",
          "T[12] ΔV=-0.565<br>下次supporter: Affirmation and Reassurance, Restatement or Paraphrasing, Question<br>supporter段: T[14~16]",
          "T[13] ΔV=0.128<br>下次supporter: Affirmation and Reassurance, Restatement or Paraphrasing, Question<br>supporter段: T[14~16]",
          "T[17] ΔV=-0.287<br>下次supporter: Restatement or Paraphrasing<br>supporter段: T[18~18]",
          "T[19] ΔV=-0.245<br>下次supporter: Reflection of feelings, Restatement or Paraphrasing<br>supporter段: T[20~21]",
          "T[22] ΔV=-0.256<br>下次supporter: Providing Suggestions<br>supporter段: T[23~23]",
          "T[24] ΔV=-0.175<br>下次supporter: Affirmation and Reassurance<br>supporter段: T[25~25]",
          "T[26] ΔV=0.331<br>下次supporter: Others, Reflection of feelings<br>supporter段: T[27~28]",
          "T[29] ΔV=0.559<br>下次supporter: Self-disclosure<br>supporter段: T[31~32]",
          "T[30] ΔV=0.173<br>下次supporter: Self-disclosure<br>supporter段: T[31~32]",
          "T[33] ΔV=-0.739<br>下次supporter: Restatement or Paraphrasing<br>supporter段: T[34~34]",
          "T[35] ΔV=-0.109<br>下次supporter: Affirmation and Reassurance<br>supporter段: T[36~36]",
          "T[37] ΔV=-0.156<br>下次supporter: Others<br>supporter段: T[39~39]",
          "T[38] ΔV=-0.213<br>下次supporter: Others<br>supporter段: T[39~39]",
          "T[40] ΔV=-0.293<br>下次supporter: Providing Suggestions, Others<br>supporter段: T[41~42]",
          "T[43] ΔV=-0.362<br>下次supporter: Others<br>supporter段: T[44~44]",
          "T[45] ΔV=-0.290<br>下次supporter: Question<br>supporter段: T[47~47]",
          "T[46] ΔV=-0.072<br>下次supporter: Question<br>supporter段: T[47~47]"
        ],
        "strategies": [
          [
            "Restatement or Paraphrasing"
          ],
          [
            "Affirmation and Reassurance",
            "Providing Suggestions"
          ],
          [
            "Affirmation and Reassurance",
            "Providing Suggestions"
          ],
          [
            "Affirmation and Reassurance",
            "Information"
          ],
          [
            "Affirmation and Reassurance",
            "Information"
          ],
          [
            "Affirmation and Reassurance",
            "Restatement or Paraphrasing",
            "Question"
          ],
          [
            "Affirmation and Reassurance",
            "Restatement or Paraphrasing",
            "Question"
          ],
          [
            "Restatement or Paraphrasing"
          ],
          [
            "Reflection of feelings",
            "Restatement or Paraphrasing"
          ],
          [
            "Providing Suggestions"
          ],
          [
            "Affirmation and Reassurance"
          ],
          [
            "Others",
            "Reflection of feelings"
          ],
          [
            "Self-disclosure",
            "Self-disclosure"
          ],
          [
            "Self-disclosure",
            "Self-disclosure"
          ],
          [
            "Restatement or Paraphrasing"
          ],
          [
            "Affirmation and Reassurance"
          ],
          [
            "Others"
          ],
          [
            "Others"
          ],
          [
            "Providing Suggestions",
            "Others"
          ],
          [
            "Others"
          ],
          [
            "Question"
          ],
          [
            "Question"
          ]
        ],
        "strategy_summary": [
          "Restatement or Paraphrasing",
          "Affirmation and Reassurance, Providing Suggestions",
          "Affirmation and Reassurance, Providing Suggestions",
          "Affirmation and Reassurance, Information",
          "Affirmation and Reassurance, Information",
          "Affirmation and Reassurance, Restatement or Paraphrasing, Question",
          "Affirmation and Reassurance, Restatement or Paraphrasing, Question",
          "Restatement or Paraphrasing",
          "Reflection of feelings, Restatement or Paraphrasing",
          "Providing Suggestions",
          "Affirmation and Reassurance",
          "Others, Reflection of feelings",
          "Self-disclosure",
          "Self-disclosure",
          "Restatement or Paraphrasing",
          "Affirmation and Reassurance",
          "Others",
          "Others",
          "Providing Suggestions, Others",
          "Others",
          "Question",
          "Question"
        ]
      },
      "strategy_prev": {
        "Restatement or Paraphrasing": {
          "x": [
            24.0,
            138.0,
            162.5,
            184.5,
            280.0
          ],
          "y": [
            -0.5170181393623352,
            -0.16457557678222656,
            -0.2985039949417114,
            -0.16367340087890625,
            -0.5379452705383301
          ],
          "hover": [
            "T[4] | 上次supporter策略: Restatement or Paraphrasing",
            "T[17] | 上次supporter策略: Restatement or Paraphrasing",
            "T[19] | 上次supporter策略: Restatement or Paraphrasing",
            "T[22] | 上次supporter策略: Restatement or Paraphrasing",
            "T[35] | 上次supporter策略: Restatement or Paraphrasing"
          ],
          "turns": [
            4,
            17,
            19,
            22,
            35
          ]
        },
        "Affirmation and Reassurance": {
          "x": [
            62.5,
            111.0,
            139.0,
            230.0,
            290.0
          ],
          "y": [
            0.020443439483642578,
            -0.4379976987838745,
            -0.16457557678222656,
            0.03232860565185547,
            0.16574597358703613
          ],
          "hover": [
            "T[8] | 上次supporter策略: Affirmation and Reassurance",
            "T[12] | 上次supporter策略: Affirmation and Reassurance",
            "T[17] | 上次supporter策略: Affirmation and Reassurance",
            "T[26] | 上次supporter策略: Affirmation and Reassurance",
            "T[37] | 上次supporter策略: Affirmation and Reassurance"
          ],
          "turns": [
            8,
            12,
            17,
            26,
            37
          ]
        },
        "Providing Suggestions": {
          "x": [
            61.5,
            208.5,
            311.0
          ],
          "y": [
            0.020443439483642578,
            -0.3003067970275879,
            -0.41151177883148193
          ],
          "hover": [
            "T[8] | 上次supporter策略: Providing Suggestions",
            "T[24] | 上次supporter策略: Providing Suggestions",
            "T[43] | 上次supporter策略: Providing Suggestions"
          ],
          "turns": [
            8,
            24,
            43
          ]
        },
        "Information": {
          "x": [
            110.0
          ],
          "y": [
            -0.4379976987838745
          ],
          "hover": [
            "T[12] | 上次supporter策略: Information"
          ],
          "turns": [
            12
          ]
        },
        "Question": {
          "x": [
            137.0
          ],
          "y": [
            -0.16457557678222656
          ],
          "hover": [
            "T[17] | 上次supporter策略: Question"
          ],
          "turns": [
            17
          ]
        },
        "Reflection of feelings": {
          "x": [
            185.5,
            243.0
          ],
          "y": [
            -0.16367340087890625,
            0.46431398391723633
          ],
          "hover": [
            "T[22] | 上次supporter策略: Reflection of feelings",
            "T[29] | 上次supporter策略: Reflection of feelings"
          ],
          "turns": [
            22,
            29
          ]
        },
        "Others": {
          "x": [
            244.0,
            305.0,
            310.0,
            318.5
          ],
          "y": [
            0.46431398391723633,
            -0.20382297039031982,
            -0.41151177883148193,
            -0.31336164474487305
          ],
          "hover": [
            "T[29] | 上次supporter策略: Others",
            "T[40] | 上次supporter策略: Others",
            "T[43] | 上次supporter策略: Others",
            "T[45] | 上次supporter策略: Others"
          ],
          "turns": [
            29,
            40,
            43,
            45
          ]
        },
        "Self-disclosure": {
          "x": [
            264.5
          ],
          "y": [
            0.2511739730834961
          ],
          "hover": [
            "T[33] | 上次supporter策略: Self-disclosure"
          ],
          "turns": [
            33
          ]
        }
      },
      "strategy_next": {
        "Restatement or Paraphrasing": {
          "x": [
            11.5,
            124.5,
            141.0,
            165.5,
            266.5
          ],
          "y": [
            -0.07194876670837402,
            0.12762212753295898,
            -0.28736042976379395,
            -0.24541723728179932,
            -0.7392621040344238
          ],
          "hover": [
            "T[2] | 下次supporter策略: Restatement or Paraphrasing",
            "T[13] | 下次supporter策略: Restatement or Paraphrasing",
            "T[17] | 下次supporter策略: Restatement or Paraphrasing",
            "T[19] | 下次supporter策略: Restatement or Paraphrasing",
            "T[33] | 下次supporter策略: Restatement or Paraphrasing"
          ],
          "turns": [
            2,
            13,
            17,
            19,
            33
          ]
        },
        "Affirmation and Reassurance": {
          "x": [
            40.0,
            97.5,
            123.5,
            210.5,
            282.0
          ],
          "y": [
            -0.23014408349990845,
            -0.4157372713088989,
            0.12762212753295898,
            -0.17499876022338867,
            -0.10929012298583984
          ],
          "hover": [
            "T[5] | 下次supporter策略: Affirmation and Reassurance",
            "T[9] | 下次supporter策略: Affirmation and Reassurance",
            "T[13] | 下次supporter策略: Affirmation and Reassurance",
            "T[24] | 下次supporter策略: Affirmation and Reassurance",
            "T[35] | 下次supporter策略: Affirmation and Reassurance"
          ],
          "turns": [
            5,
            9,
            13,
            24,
            35
          ]
        },
        "Providing Suggestions": {
          "x": [
            41.0,
            187.5,
            307.0
          ],
          "y": [
            -0.23014408349990845,
            -0.2561492919921875,
            -0.29340970516204834
          ],
          "hover": [
            "T[5] | 下次supporter策略: Providing Suggestions",
            "T[22] | 下次supporter策略: Providing Suggestions",
            "T[40] | 下次supporter策略: Providing Suggestions"
          ],
          "turns": [
            5,
            22,
            40
          ]
        },
        "Information": {
          "x": [
            98.5
          ],
          "y": [
            -0.4157372713088989
          ],
          "hover": [
            "T[9] | 下次supporter策略: Information"
          ],
          "turns": [
            9
          ]
        },
        "Question": {
          "x": [
            125.5,
            326.0
          ],
          "y": [
            0.12762212753295898,
            -0.07186007499694824
          ],
          "hover": [
            "T[13] | 下次supporter策略: Question",
            "T[46] | 下次supporter策略: Question"
          ],
          "turns": [
            13,
            46
          ]
        },
        "Reflection of feelings": {
          "x": [
            164.5,
            233.0
          ],
          "y": [
            -0.24541723728179932,
            0.33104968070983887
          ],
          "hover": [
            "T[19] | 下次supporter策略: Reflection of feelings",
            "T[26] | 下次supporter策略: Reflection of feelings"
          ],
          "turns": [
            19,
            26
          ]
        },
        "Others": {
          "x": [
            232.0,
            301.0,
            308.0,
            313.0
          ],
          "y": [
            0.33104968070983887,
            -0.21306753158569336,
            -0.29340970516204834,
            -0.3616853952407837
          ],
          "hover": [
            "T[26] | 下次supporter策略: Others",
            "T[38] | 下次supporter策略: Others",
            "T[40] | 下次supporter策略: Others",
            "T[43] | 下次supporter策略: Others"
          ],
          "turns": [
            26,
            38,
            40,
            43
          ]
        },
        "Self-disclosure": {
          "x": [
            254.0
          ],
          "y": [
            0.17279481887817383
          ],
          "hover": [
            "T[30] | 下次supporter策略: Self-disclosure"
          ],
          "turns": [
            30
          ]
        }
      }
    },
    "arousal": {
      "is_sent": true,
      "turn_to_x": {
        "1": 2.5,
        "2": 10.5,
        "4": 25.0,
        "5": 39.0,
        "8": 63.5,
        "9": 96.5,
        "12": 112.0,
        "13": 122.5,
        "17": 140.0,
        "19": 163.5,
        "22": 186.5,
        "24": 209.5,
        "26": 231.0,
        "29": 245.0,
        "30": 253.0,
        "33": 265.5,
        "35": 281.0,
        "37": 291.0,
        "38": 300.0,
        "40": 306.0,
        "43": 312.0,
        "45": 319.5,
        "46": 325.0
      },
      "seeker_curve": {
        "x": [
          0.0,
          6.0,
          16.0,
          35.0,
          44.0,
          84.0,
          110.0,
          115.0,
          131.0,
          150.0,
          178.0,
          196.0,
          224.0,
          239.0,
          252.0,
          255.0,
          277.0,
          286.0,
          297.0,
          304.0,
          309.0,
          316.0,
          324.0
        ],
        "y": [
          -0.015990018844604492,
          0.11302304267883301,
          0.0343172550201416,
          -0.0357666015625,
          0.04935884475708008,
          0.0785977840423584,
          0.07733535766601562,
          0.008986592292785645,
          0.050464749336242676,
          0.018169403076171875,
          -0.0360407829284668,
          -0.02083587646484375,
          0.12755918502807617,
          0.08155989646911621,
          0.10805642604827881,
          -0.040985822677612305,
          0.1538841724395752,
          0.0664207935333252,
          0.06496810913085938,
          0.1188197135925293,
          0.14809942245483398,
          0.09956037998199463,
          0.06878161430358887
        ],
        "turns": [
          1,
          2,
          4,
          5,
          8,
          9,
          12,
          13,
          17,
          19,
          22,
          24,
          26,
          29,
          30,
          33,
          35,
          37,
          38,
          40,
          43,
          45,
          46
        ]
      },
      "prev": {
        "x": [
          10.5,
          25.0,
          39.0,
          63.5,
          96.5,
          112.0,
          122.5,
          140.0,
          163.5,
          186.5,
          209.5,
          231.0,
          245.0,
          253.0,
          265.5,
          281.0,
          291.0,
          300.0,
          306.0,
          312.0,
          319.5,
          325.0
        ],
        "y": [
          -0.25511860847473145,
          0.1512690782546997,
          0.09400951862335205,
          -0.008739948272705078,
          0.008283376693725586,
          0.027359843254089355,
          -0.035051584243774414,
          -0.07429325580596924,
          -0.04014003276824951,
          -0.02416205406188965,
          -0.09832906723022461,
          0.06072962284088135,
          0.031084060668945312,
          -0.038930535316467285,
          -0.09212839603424072,
          -0.5435932874679565,
          0.05465054512023926,
          0.0008560419082641602,
          -0.12994122505187988,
          -0.3251032829284668,
          -0.29369521141052246,
          -0.21954846382141113
        ],
        "turns": [
          2,
          4,
          5,
          8,
          9,
          12,
          13,
          17,
          19,
          22,
          24,
          26,
          29,
          30,
          33,
          35,
          37,
          38,
          40,
          43,
          45,
          46
        ],
        "hover": [
          "T[2] ΔA=-0.255<br>上次supporter: Question<br>supporter段: T[0~0]",
          "T[4] ΔA=0.151<br>上次supporter: Restatement or Paraphrasing<br>supporter段: T[3~3]",
          "T[5] ΔA=0.094<br>上次supporter: Restatement or Paraphrasing<br>supporter段: T[3~3]",
          "T[8] ΔA=-0.009<br>上次supporter: Affirmation and Reassurance, Providing Suggestions<br>supporter段: T[6~7]",
          "T[9] ΔA=0.008<br>上次supporter: Affirmation and Reassurance, Providing Suggestions<br>supporter段: T[6~7]",
          "T[12] ΔA=0.027<br>上次supporter: Affirmation and Reassurance, Information<br>supporter段: T[10~11]",
          "T[13] ΔA=-0.035<br>上次supporter: Affirmation and Reassurance, Information<br>supporter段: T[10~11]",
          "T[17] ΔA=-0.074<br>上次supporter: Affirmation and Reassurance, Restatement or Paraphrasing, Question<br>supporter段: T[14~16]",
          "T[19] ΔA=-0.040<br>上次supporter: Restatement or Paraphrasing<br>supporter段: T[18~18]",
          "T[22] ΔA=-0.024<br>上次supporter: Reflection of feelings, Restatement or Paraphrasing<br>supporter段: T[20~21]",
          "T[24] ΔA=-0.098<br>上次supporter: Providing Suggestions<br>supporter段: T[23~23]",
          "T[26] ΔA=0.061<br>上次supporter: Affirmation and Reassurance<br>supporter段: T[25~25]",
          "T[29] ΔA=0.031<br>上次supporter: Others, Reflection of feelings<br>supporter段: T[27~28]",
          "T[30] ΔA=-0.039<br>上次supporter: Others, Reflection of feelings<br>supporter段: T[27~28]",
          "T[33] ΔA=-0.092<br>上次supporter: Self-disclosure<br>supporter段: T[31~32]",
          "T[35] ΔA=-0.544<br>上次supporter: Restatement or Paraphrasing<br>supporter段: T[34~34]",
          "T[37] ΔA=0.055<br>上次supporter: Affirmation and Reassurance<br>supporter段: T[36~36]",
          "T[38] ΔA=0.001<br>上次supporter: Affirmation and Reassurance<br>supporter段: T[36~36]",
          "T[40] ΔA=-0.130<br>上次supporter: Others<br>supporter段: T[39~39]",
          "T[43] ΔA=-0.325<br>上次supporter: Providing Suggestions, Others<br>supporter段: T[41~42]",
          "T[45] ΔA=-0.294<br>上次supporter: Others<br>supporter段: T[44~44]",
          "T[46] ΔA=-0.220<br>上次supporter: Others<br>supporter段: T[44~44]"
        ],
        "strategies": [
          [
            "Question"
          ],
          [
            "Restatement or Paraphrasing"
          ],
          [
            "Restatement or Paraphrasing"
          ],
          [
            "Affirmation and Reassurance",
            "Providing Suggestions"
          ],
          [
            "Affirmation and Reassurance",
            "Providing Suggestions"
          ],
          [
            "Affirmation and Reassurance",
            "Information"
          ],
          [
            "Affirmation and Reassurance",
            "Information"
          ],
          [
            "Affirmation and Reassurance",
            "Restatement or Paraphrasing",
            "Question"
          ],
          [
            "Restatement or Paraphrasing"
          ],
          [
            "Reflection of feelings",
            "Restatement or Paraphrasing"
          ],
          [
            "Providing Suggestions"
          ],
          [
            "Affirmation and Reassurance"
          ],
          [
            "Others",
            "Reflection of feelings"
          ],
          [
            "Others",
            "Reflection of feelings"
          ],
          [
            "Self-disclosure",
            "Self-disclosure"
          ],
          [
            "Restatement or Paraphrasing"
          ],
          [
            "Affirmation and Reassurance"
          ],
          [
            "Affirmation and Reassurance"
          ],
          [
            "Others"
          ],
          [
            "Providing Suggestions",
            "Others"
          ],
          [
            "Others"
          ],
          [
            "Others"
          ]
        ],
        "strategy_summary": [
          "Question",
          "Restatement or Paraphrasing",
          "Restatement or Paraphrasing",
          "Affirmation and Reassurance, Providing Suggestions",
          "Affirmation and Reassurance, Providing Suggestions",
          "Affirmation and Reassurance, Information",
          "Affirmation and Reassurance, Information",
          "Affirmation and Reassurance, Restatement or Paraphrasing, Question",
          "Restatement or Paraphrasing",
          "Reflection of feelings, Restatement or Paraphrasing",
          "Providing Suggestions",
          "Affirmation and Reassurance",
          "Others, Reflection of feelings",
          "Others, Reflection of feelings",
          "Self-disclosure",
          "Restatement or Paraphrasing",
          "Affirmation and Reassurance",
          "Affirmation and Reassurance",
          "Others",
          "Providing Suggestions, Others",
          "Others",
          "Others"
        ]
      },
      "next": {
        "x": [
          10.5,
          25.0,
          39.0,
          63.5,
          96.5,
          112.0,
          122.5,
          140.0,
          163.5,
          186.5,
          209.5,
          231.0,
          245.0,
          253.0,
          265.5,
          281.0,
          291.0,
          300.0,
          306.0,
          312.0,
          319.5,
          325.0
        ],
        "y": [
          -0.005218029022216797,
          0.12262213230133057,
          0.06536257266998291,
          -0.010341644287109375,
          0.006681680679321289,
          -0.012635111808776855,
          -0.07504653930664062,
          -0.07024836540222168,
          0.026708364486694336,
          -0.06824624538421631,
          0.04136180877685547,
          -0.11475026607513428,
          0.07328653335571289,
          0.003271937370300293,
          -0.5755599737167358,
          -0.08682453632354736,
          -0.12073516845703125,
          -0.17452967166900635,
          -0.3519552946090698,
          -0.20605826377868652,
          -0.31117379665374756,
          -0.23702704906463623
        ],
        "turns": [
          2,
          4,
          5,
          8,
          9,
          12,
          13,
          17,
          19,
          22,
          24,
          26,
          29,
          30,
          33,
          35,
          37,
          38,
          40,
          43,
          45,
          46
        ],
        "hover": [
          "T[2] ΔA=-0.005<br>下次supporter: Restatement or Paraphrasing<br>supporter段: T[3~3]",
          "T[4] ΔA=0.123<br>下次supporter: Affirmation and Reassurance, Providing Suggestions<br>supporter段: T[6~7]",
          "T[5] ΔA=0.065<br>下次supporter: Affirmation and Reassurance, Providing Suggestions<br>supporter段: T[6~7]",
          "T[8] ΔA=-0.010<br>下次supporter: Affirmation and Reassurance, Information<br>supporter段: T[10~11]",
          "T[9] ΔA=0.007<br>下次supporter: Affirmation and Reassurance, Information<br>supporter段: T[10~11]",
          "T[12] ΔA=-0.013<br>下次supporter: Affirmation and Reassurance, Restatement or Paraphrasing, Question<br>supporter段: T[14~16]",
          "T[13] ΔA=-0.075<br>下次supporter: Affirmation and Reassurance, Restatement or Paraphrasing, Question<br>supporter段: T[14~16]",
          "T[17] ΔA=-0.070<br>下次supporter: Restatement or Paraphrasing<br>supporter段: T[18~18]",
          "T[19] ΔA=0.027<br>下次supporter: Reflection of feelings, Restatement or Paraphrasing<br>supporter段: T[20~21]",
          "T[22] ΔA=-0.068<br>下次supporter: Providing Suggestions<br>supporter段: T[23~23]",
          "T[24] ΔA=0.041<br>下次supporter: Affirmation and Reassurance<br>supporter段: T[25~25]",
          "T[26] ΔA=-0.115<br>下次supporter: Others, Reflection of feelings<br>supporter段: T[27~28]",
          "T[29] ΔA=0.073<br>下次supporter: Self-disclosure<br>supporter段: T[31~32]",
          "T[30] ΔA=0.003<br>下次supporter: Self-disclosure<br>supporter段: T[31~32]",
          "T[33] ΔA=-0.576<br>下次supporter: Restatement or Paraphrasing<br>supporter段: T[34~34]",
          "T[35] ΔA=-0.087<br>下次supporter: Affirmation and Reassurance<br>supporter段: T[36~36]",
          "T[37] ΔA=-0.121<br>下次supporter: Others<br>supporter段: T[39~39]",
          "T[38] ΔA=-0.175<br>下次supporter: Others<br>supporter段: T[39~39]",
          "T[40] ΔA=-0.352<br>下次supporter: Providing Suggestions, Others<br>supporter段: T[41~42]",
          "T[43] ΔA=-0.206<br>下次supporter: Others<br>supporter段: T[44~44]",
          "T[45] ΔA=-0.311<br>下次supporter: Question<br>supporter段: T[47~47]",
          "T[46] ΔA=-0.237<br>下次supporter: Question<br>supporter段: T[47~47]"
        ],
        "strategies": [
          [
            "Restatement or Paraphrasing"
          ],
          [
            "Affirmation and Reassurance",
            "Providing Suggestions"
          ],
          [
            "Affirmation and Reassurance",
            "Providing Suggestions"
          ],
          [
            "Affirmation and Reassurance",
            "Information"
          ],
          [
            "Affirmation and Reassurance",
            "Information"
          ],
          [
            "Affirmation and Reassurance",
            "Restatement or Paraphrasing",
            "Question"
          ],
          [
            "Affirmation and Reassurance",
            "Restatement or Paraphrasing",
            "Question"
          ],
          [
            "Restatement or Paraphrasing"
          ],
          [
            "Reflection of feelings",
            "Restatement or Paraphrasing"
          ],
          [
            "Providing Suggestions"
          ],
          [
            "Affirmation and Reassurance"
          ],
          [
            "Others",
            "Reflection of feelings"
          ],
          [
            "Self-disclosure",
            "Self-disclosure"
          ],
          [
            "Self-disclosure",
            "Self-disclosure"
          ],
          [
            "Restatement or Paraphrasing"
          ],
          [
            "Affirmation and Reassurance"
          ],
          [
            "Others"
          ],
          [
            "Others"
          ],
          [
            "Providing Suggestions",
            "Others"
          ],
          [
            "Others"
          ],
          [
            "Question"
          ],
          [
            "Question"
          ]
        ],
        "strategy_summary": [
          "Restatement or Paraphrasing",
          "Affirmation and Reassurance, Providing Suggestions",
          "Affirmation and Reassurance, Providing Suggestions",
          "Affirmation and Reassurance, Information",
          "Affirmation and Reassurance, Information",
          "Affirmation and Reassurance, Restatement or Paraphrasing, Question",
          "Affirmation and Reassurance, Restatement or Paraphrasing, Question",
          "Restatement or Paraphrasing",
          "Reflection of feelings, Restatement or Paraphrasing",
          "Providing Suggestions",
          "Affirmation and Reassurance",
          "Others, Reflection of feelings",
          "Self-disclosure",
          "Self-disclosure",
          "Restatement or Paraphrasing",
          "Affirmation and Reassurance",
          "Others",
          "Others",
          "Providing Suggestions, Others",
          "Others",
          "Question",
          "Question"
        ]
      },
      "strategy_prev": {
        "Restatement or Paraphrasing": {
          "x": [
            24.0,
            138.0,
            162.5,
            184.5,
            280.0
          ],
          "y": [
            0.1512690782546997,
            -0.07429325580596924,
            -0.04014003276824951,
            -0.02416205406188965,
            -0.5435932874679565
          ],
          "hover": [
            "T[4] | 上次supporter策略: Restatement or Paraphrasing",
            "T[17] | 上次supporter策略: Restatement or Paraphrasing",
            "T[19] | 上次supporter策略: Restatement or Paraphrasing",
            "T[22] | 上次supporter策略: Restatement or Paraphrasing",
            "T[35] | 上次supporter策略: Restatement or Paraphrasing"
          ],
          "turns": [
            4,
            17,
            19,
            22,
            35
          ]
        },
        "Affirmation and Reassurance": {
          "x": [
            62.5,
            111.0,
            139.0,
            230.0,
            290.0
          ],
          "y": [
            -0.008739948272705078,
            0.027359843254089355,
            -0.07429325580596924,
            0.06072962284088135,
            0.05465054512023926
          ],
          "hover": [
            "T[8] | 上次supporter策略: Affirmation and Reassurance",
            "T[12] | 上次supporter策略: Affirmation and Reassurance",
            "T[17] | 上次supporter策略: Affirmation and Reassurance",
            "T[26] | 上次supporter策略: Affirmation and Reassurance",
            "T[37] | 上次supporter策略: Affirmation and Reassurance"
          ],
          "turns": [
            8,
            12,
            17,
            26,
            37
          ]
        },
        "Providing Suggestions": {
          "x": [
            61.5,
            208.5,
            311.0
          ],
          "y": [
            -0.008739948272705078,
            -0.09832906723022461,
            -0.3251032829284668
          ],
          "hover": [
            "T[8] | 上次supporter策略: Providing Suggestions",
            "T[24] | 上次supporter策略: Providing Suggestions",
            "T[43] | 上次supporter策略: Providing Suggestions"
          ],
          "turns": [
            8,
            24,
            43
          ]
        },
        "Information": {
          "x": [
            110.0
          ],
          "y": [
            0.027359843254089355
          ],
          "hover": [
            "T[12] | 上次supporter策略: Information"
          ],
          "turns": [
            12
          ]
        },
        "Question": {
          "x": [
            137.0
          ],
          "y": [
            -0.07429325580596924
          ],
          "hover": [
            "T[17] | 上次supporter策略: Question"
          ],
          "turns": [
            17
          ]
        },
        "Reflection of feelings": {
          "x": [
            185.5,
            243.0
          ],
          "y": [
            -0.02416205406188965,
            0.031084060668945312
          ],
          "hover": [
            "T[22] | 上次supporter策略: Reflection of feelings",
            "T[29] | 上次supporter策略: Reflection of feelings"
          ],
          "turns": [
            22,
            29
          ]
        },
        "Others": {
          "x": [
            244.0,
            305.0,
            310.0,
            318.5
          ],
          "y": [
            0.031084060668945312,
            -0.12994122505187988,
            -0.3251032829284668,
            -0.29369521141052246
          ],
          "hover": [
            "T[29] | 上次supporter策略: Others",
            "T[40] | 上次supporter策略: Others",
            "T[43] | 上次supporter策略: Others",
            "T[45] | 上次supporter策略: Others"
          ],
          "turns": [
            29,
            40,
            43,
            45
          ]
        },
        "Self-disclosure": {
          "x": [
            264.5
          ],
          "y": [
            -0.09212839603424072
          ],
          "hover": [
            "T[33] | 上次supporter策略: Self-disclosure"
          ],
          "turns": [
            33
          ]
        }
      },
      "strategy_next": {
        "Restatement or Paraphrasing": {
          "x": [
            11.5,
            124.5,
            141.0,
            165.5,
            266.5
          ],
          "y": [
            -0.005218029022216797,
            -0.07504653930664062,
            -0.07024836540222168,
            0.026708364486694336,
            -0.5755599737167358
          ],
          "hover": [
            "T[2] | 下次supporter策略: Restatement or Paraphrasing",
            "T[13] | 下次supporter策略: Restatement or Paraphrasing",
            "T[17] | 下次supporter策略: Restatement or Paraphrasing",
            "T[19] | 下次supporter策略: Restatement or Paraphrasing",
            "T[33] | 下次supporter策略: Restatement or Paraphrasing"
          ],
          "turns": [
            2,
            13,
            17,
            19,
            33
          ]
        },
        "Affirmation and Reassurance": {
          "x": [
            40.0,
            97.5,
            123.5,
            210.5,
            282.0
          ],
          "y": [
            0.06536257266998291,
            0.006681680679321289,
            -0.07504653930664062,
            0.04136180877685547,
            -0.08682453632354736
          ],
          "hover": [
            "T[5] | 下次supporter策略: Affirmation and Reassurance",
            "T[9] | 下次supporter策略: Affirmation and Reassurance",
            "T[13] | 下次supporter策略: Affirmation and Reassurance",
            "T[24] | 下次supporter策略: Affirmation and Reassurance",
            "T[35] | 下次supporter策略: Affirmation and Reassurance"
          ],
          "turns": [
            5,
            9,
            13,
            24,
            35
          ]
        },
        "Providing Suggestions": {
          "x": [
            41.0,
            187.5,
            307.0
          ],
          "y": [
            0.06536257266998291,
            -0.06824624538421631,
            -0.3519552946090698
          ],
          "hover": [
            "T[5] | 下次supporter策略: Providing Suggestions",
            "T[22] | 下次supporter策略: Providing Suggestions",
            "T[40] | 下次supporter策略: Providing Suggestions"
          ],
          "turns": [
            5,
            22,
            40
          ]
        },
        "Information": {
          "x": [
            98.5
          ],
          "y": [
            0.006681680679321289
          ],
          "hover": [
            "T[9] | 下次supporter策略: Information"
          ],
          "turns": [
            9
          ]
        },
        "Question": {
          "x": [
            125.5,
            326.0
          ],
          "y": [
            -0.07504653930664062,
            -0.23702704906463623
          ],
          "hover": [
            "T[13] | 下次supporter策略: Question",
            "T[46] | 下次supporter策略: Question"
          ],
          "turns": [
            13,
            46
          ]
        },
        "Reflection of feelings": {
          "x": [
            164.5,
            233.0
          ],
          "y": [
            0.026708364486694336,
            -0.11475026607513428
          ],
          "hover": [
            "T[19] | 下次supporter策略: Reflection of feelings",
            "T[26] | 下次supporter策略: Reflection of feelings"
          ],
          "turns": [
            19,
            26
          ]
        },
        "Others": {
          "x": [
            232.0,
            301.0,
            308.0,
            313.0
          ],
          "y": [
            -0.11475026607513428,
            -0.17452967166900635,
            -0.3519552946090698,
            -0.20605826377868652
          ],
          "hover": [
            "T[26] | 下次supporter策略: Others",
            "T[38] | 下次supporter策略: Others",
            "T[40] | 下次supporter策略: Others",
            "T[43] | 下次supporter策略: Others"
          ],
          "turns": [
            26,
            38,
            40,
            43
          ]
        },
        "Self-disclosure": {
          "x": [
            254.0
          ],
          "y": [
            0.003271937370300293
          ],
          "hover": [
            "T[30] | 下次supporter策略: Self-disclosure"
          ],
          "turns": [
            30
          ]
        }
      }
    },
    "dominance": {
      "is_sent": true,
      "turn_to_x": {
        "1": 2.5,
        "2": 10.5,
        "4": 25.0,
        "5": 39.0,
        "8": 63.5,
        "9": 96.5,
        "12": 112.0,
        "13": 122.5,
        "17": 140.0,
        "19": 163.5,
        "22": 186.5,
        "24": 209.5,
        "26": 231.0,
        "29": 245.0,
        "30": 253.0,
        "33": 265.5,
        "35": 281.0,
        "37": 291.0,
        "38": 300.0,
        "40": 306.0,
        "43": 312.0,
        "45": 319.5,
        "46": 325.0
      },
      "seeker_curve": {
        "x": [
          0.0,
          6.0,
          16.0,
          35.0,
          44.0,
          84.0,
          110.0,
          115.0,
          131.0,
          150.0,
          178.0,
          196.0,
          224.0,
          239.0,
          252.0,
          255.0,
          277.0,
          286.0,
          297.0,
          304.0,
          309.0,
          316.0,
          324.0
        ],
        "y": [
          0.02246701717376709,
          -0.16287577152252197,
          -0.1666356325149536,
          -0.15580213069915771,
          -0.008571147918701172,
          -0.1919116973876953,
          0.15478718280792236,
          0.06059598922729492,
          -0.09366416931152344,
          0.08686530590057373,
          -0.06357216835021973,
          0.002100825309753418,
          0.11076796054840088,
          0.007733583450317383,
          0.09472370147705078,
          -0.00954437255859375,
          0.08361697196960449,
          0.09586596488952637,
          0.038355231285095215,
          0.0928964614868164,
          0.09785997867584229,
          0.08475041389465332,
          -0.01929020881652832
        ],
        "turns": [
          1,
          2,
          4,
          5,
          8,
          9,
          12,
          13,
          17,
          19,
          22,
          24,
          26,
          29,
          30,
          33,
          35,
          37,
          38,
          40,
          43,
          45,
          46
        ]
      },
      "prev": {
        "x": [
          10.5,
          25.0,
          39.0,
          63.5,
          96.5,
          112.0,
          122.5,
          140.0,
          163.5,
          186.5,
          209.5,
          231.0,
          245.0,
          253.0,
          265.5,
          281.0,
          291.0,
          300.0,
          306.0,
          312.0,
          319.5,
          325.0
        ],
        "y": [
          -0.07235968112945557,
          -0.1918778419494629,
          -0.24037671089172363,
          0.028895020484924316,
          -0.06690192222595215,
          -0.15509247779846191,
          0.10128188133239746,
          -0.07993900775909424,
          -0.14606285095214844,
          -0.07424235343933105,
          -0.12970256805419922,
          0.012168645858764648,
          0.18349993228912354,
          0.09927892684936523,
          0.10701334476470947,
          -0.19305169582366943,
          -0.01361989974975586,
          -0.019766807556152344,
          -0.04256713390350342,
          -0.06581926345825195,
          -0.04224503040313721,
          -0.03551828861236572
        ],
        "turns": [
          2,
          4,
          5,
          8,
          9,
          12,
          13,
          17,
          19,
          22,
          24,
          26,
          29,
          30,
          33,
          35,
          37,
          38,
          40,
          43,
          45,
          46
        ],
        "hover": [
          "T[2] ΔD=-0.072<br>上次supporter: Question<br>supporter段: T[0~0]",
          "T[4] ΔD=-0.192<br>上次supporter: Restatement or Paraphrasing<br>supporter段: T[3~3]",
          "T[5] ΔD=-0.240<br>上次supporter: Restatement or Paraphrasing<br>supporter段: T[3~3]",
          "T[8] ΔD=0.029<br>上次supporter: Affirmation and Reassurance, Providing Suggestions<br>supporter段: T[6~7]",
          "T[9] ΔD=-0.067<br>上次supporter: Affirmation and Reassurance, Providing Suggestions<br>supporter段: T[6~7]",
          "T[12] ΔD=-0.155<br>上次supporter: Affirmation and Reassurance, Information<br>supporter段: T[10~11]",
          "T[13] ΔD=0.101<br>上次supporter: Affirmation and Reassurance, Information<br>supporter段: T[10~11]",
          "T[17] ΔD=-0.080<br>上次supporter: Affirmation and Reassurance, Restatement or Paraphrasing, Question<br>supporter段: T[14~16]",
          "T[19] ΔD=-0.146<br>上次supporter: Restatement or Paraphrasing<br>supporter段: T[18~18]",
          "T[22] ΔD=-0.074<br>上次supporter: Reflection of feelings, Restatement or Paraphrasing<br>supporter段: T[20~21]",
          "T[24] ΔD=-0.130<br>上次supporter: Providing Suggestions<br>supporter段: T[23~23]",
          "T[26] ΔD=0.012<br>上次supporter: Affirmation and Reassurance<br>supporter段: T[25~25]",
          "T[29] ΔD=0.183<br>上次supporter: Others, Reflection of feelings<br>supporter段: T[27~28]",
          "T[30] ΔD=0.099<br>上次supporter: Others, Reflection of feelings<br>supporter段: T[27~28]",
          "T[33] ΔD=0.107<br>上次supporter: Self-disclosure<br>supporter段: T[31~32]",
          "T[35] ΔD=-0.193<br>上次supporter: Restatement or Paraphrasing<br>supporter段: T[34~34]",
          "T[37] ΔD=-0.014<br>上次supporter: Affirmation and Reassurance<br>supporter段: T[36~36]",
          "T[38] ΔD=-0.020<br>上次supporter: Affirmation and Reassurance<br>supporter段: T[36~36]",
          "T[40] ΔD=-0.043<br>上次supporter: Others<br>supporter段: T[39~39]",
          "T[43] ΔD=-0.066<br>上次supporter: Providing Suggestions, Others<br>supporter段: T[41~42]",
          "T[45] ΔD=-0.042<br>上次supporter: Others<br>supporter段: T[44~44]",
          "T[46] ΔD=-0.036<br>上次supporter: Others<br>supporter段: T[44~44]"
        ],
        "strategies": [
          [
            "Question"
          ],
          [
            "Restatement or Paraphrasing"
          ],
          [
            "Restatement or Paraphrasing"
          ],
          [
            "Affirmation and Reassurance",
            "Providing Suggestions"
          ],
          [
            "Affirmation and Reassurance",
            "Providing Suggestions"
          ],
          [
            "Affirmation and Reassurance",
            "Information"
          ],
          [
            "Affirmation and Reassurance",
            "Information"
          ],
          [
            "Affirmation and Reassurance",
            "Restatement or Paraphrasing",
            "Question"
          ],
          [
            "Restatement or Paraphrasing"
          ],
          [
            "Reflection of feelings",
            "Restatement or Paraphrasing"
          ],
          [
            "Providing Suggestions"
          ],
          [
            "Affirmation and Reassurance"
          ],
          [
            "Others",
            "Reflection of feelings"
          ],
          [
            "Others",
            "Reflection of feelings"
          ],
          [
            "Self-disclosure",
            "Self-disclosure"
          ],
          [
            "Restatement or Paraphrasing"
          ],
          [
            "Affirmation and Reassurance"
          ],
          [
            "Affirmation and Reassurance"
          ],
          [
            "Others"
          ],
          [
            "Providing Suggestions",
            "Others"
          ],
          [
            "Others"
          ],
          [
            "Others"
          ]
        ],
        "strategy_summary": [
          "Question",
          "Restatement or Paraphrasing",
          "Restatement or Paraphrasing",
          "Affirmation and Reassurance, Providing Suggestions",
          "Affirmation and Reassurance, Providing Suggestions",
          "Affirmation and Reassurance, Information",
          "Affirmation and Reassurance, Information",
          "Affirmation and Reassurance, Restatement or Paraphrasing, Question",
          "Restatement or Paraphrasing",
          "Reflection of feelings, Restatement or Paraphrasing",
          "Providing Suggestions",
          "Affirmation and Reassurance",
          "Others, Reflection of feelings",
          "Others, Reflection of feelings",
          "Self-disclosure",
          "Restatement or Paraphrasing",
          "Affirmation and Reassurance",
          "Affirmation and Reassurance",
          "Others",
          "Providing Suggestions, Others",
          "Others",
          "Others"
        ]
      },
      "next": {
        "x": [
          10.5,
          25.0,
          39.0,
          63.5,
          96.5,
          112.0,
          122.5,
          140.0,
          163.5,
          186.5,
          209.5,
          231.0,
          245.0,
          253.0,
          265.5,
          281.0,
          291.0,
          300.0,
          306.0,
          312.0,
          319.5,
          325.0
        ],
        "y": [
          -0.012151479721069336,
          -0.11806368827819824,
          -0.16656255722045898,
          -0.07000720500946045,
          -0.16580414772033691,
          -0.18178009986877441,
          0.07459425926208496,
          -0.1897519826889038,
          -0.11200308799743652,
          -0.07284021377563477,
          -0.07808375358581543,
          0.14101147651672363,
          0.1989985704421997,
          0.1147775650024414,
          -0.2294478416442871,
          -0.0666513442993164,
          -0.012338757514953613,
          -0.018485665321350098,
          -0.10343790054321289,
          -0.020156025886535645,
          0.024874448776245117,
          0.0316011905670166
        ],
        "turns": [
          2,
          4,
          5,
          8,
          9,
          12,
          13,
          17,
          19,
          22,
          24,
          26,
          29,
          30,
          33,
          35,
          37,
          38,
          40,
          43,
          45,
          46
        ],
        "hover": [
          "T[2] ΔD=-0.012<br>下次supporter: Restatement or Paraphrasing<br>supporter段: T[3~3]",
          "T[4] ΔD=-0.118<br>下次supporter: Affirmation and Reassurance, Providing Suggestions<br>supporter段: T[6~7]",
          "T[5] ΔD=-0.167<br>下次supporter: Affirmation and Reassurance, Providing Suggestions<br>supporter段: T[6~7]",
          "T[8] ΔD=-0.070<br>下次supporter: Affirmation and Reassurance, Information<br>supporter段: T[10~11]",
          "T[9] ΔD=-0.166<br>下次supporter: Affirmation and Reassurance, Information<br>supporter段: T[10~11]",
          "T[12] ΔD=-0.182<br>下次supporter: Affirmation and Reassurance, Restatement or Paraphrasing, Question<br>supporter段: T[14~16]",
          "T[13] ΔD=0.075<br>下次supporter: Affirmation and Reassurance, Restatement or Paraphrasing, Question<br>supporter段: T[14~16]",
          "T[17] ΔD=-0.190<br>下次supporter: Restatement or Paraphrasing<br>supporter段: T[18~18]",
          "T[19] ΔD=-0.112<br>下次supporter: Reflection of feelings, Restatement or Paraphrasing<br>supporter段: T[20~21]",
          "T[22] ΔD=-0.073<br>下次supporter: Providing Suggestions<br>supporter段: T[23~23]",
          "T[24] ΔD=-0.078<br>下次supporter: Affirmation and Reassurance<br>supporter段: T[25~25]",
          "T[26] ΔD=0.141<br>下次supporter: Others, Reflection of feelings<br>supporter段: T[27~28]",
          "T[29] ΔD=0.199<br>下次supporter: Self-disclosure<br>supporter段: T[31~32]",
          "T[30] ΔD=0.115<br>下次supporter: Self-disclosure<br>supporter段: T[31~32]",
          "T[33] ΔD=-0.229<br>下次supporter: Restatement or Paraphrasing<br>supporter段: T[34~34]",
          "T[35] ΔD=-0.067<br>下次supporter: Affirmation and Reassurance<br>supporter段: T[36~36]",
          "T[37] ΔD=-0.012<br>下次supporter: Others<br>supporter段: T[39~39]",
          "T[38] ΔD=-0.018<br>下次supporter: Others<br>supporter段: T[39~39]",
          "T[40] ΔD=-0.103<br>下次supporter: Providing Suggestions, Others<br>supporter段: T[41~42]",
          "T[43] ΔD=-0.020<br>下次supporter: Others<br>supporter段: T[44~44]",
          "T[45] ΔD=0.025<br>下次supporter: Question<br>supporter段: T[47~47]",
          "T[46] ΔD=0.032<br>下次supporter: Question<br>supporter段: T[47~47]"
        ],
        "strategies": [
          [
            "Restatement or Paraphrasing"
          ],
          [
            "Affirmation and Reassurance",
            "Providing Suggestions"
          ],
          [
            "Affirmation and Reassurance",
            "Providing Suggestions"
          ],
          [
            "Affirmation and Reassurance",
            "Information"
          ],
          [
            "Affirmation and Reassurance",
            "Information"
          ],
          [
            "Affirmation and Reassurance",
            "Restatement or Paraphrasing",
            "Question"
          ],
          [
            "Affirmation and Reassurance",
            "Restatement or Paraphrasing",
            "Question"
          ],
          [
            "Restatement or Paraphrasing"
          ],
          [
            "Reflection of feelings",
            "Restatement or Paraphrasing"
          ],
          [
            "Providing Suggestions"
          ],
          [
            "Affirmation and Reassurance"
          ],
          [
            "Others",
            "Reflection of feelings"
          ],
          [
            "Self-disclosure",
            "Self-disclosure"
          ],
          [
            "Self-disclosure",
            "Self-disclosure"
          ],
          [
            "Restatement or Paraphrasing"
          ],
          [
            "Affirmation and Reassurance"
          ],
          [
            "Others"
          ],
          [
            "Others"
          ],
          [
            "Providing Suggestions",
            "Others"
          ],
          [
            "Others"
          ],
          [
            "Question"
          ],
          [
            "Question"
          ]
        ],
        "strategy_summary": [
          "Restatement or Paraphrasing",
          "Affirmation and Reassurance, Providing Suggestions",
          "Affirmation and Reassurance, Providing Suggestions",
          "Affirmation and Reassurance, Information",
          "Affirmation and Reassurance, Information",
          "Affirmation and Reassurance, Restatement or Paraphrasing, Question",
          "Affirmation and Reassurance, Restatement or Paraphrasing, Question",
          "Restatement or Paraphrasing",
          "Reflection of feelings, Restatement or Paraphrasing",
          "Providing Suggestions",
          "Affirmation and Reassurance",
          "Others, Reflection of feelings",
          "Self-disclosure",
          "Self-disclosure",
          "Restatement or Paraphrasing",
          "Affirmation and Reassurance",
          "Others",
          "Others",
          "Providing Suggestions, Others",
          "Others",
          "Question",
          "Question"
        ]
      },
      "strategy_prev": {
        "Restatement or Paraphrasing": {
          "x": [
            24.0,
            138.0,
            162.5,
            184.5,
            280.0
          ],
          "y": [
            -0.1918778419494629,
            -0.07993900775909424,
            -0.14606285095214844,
            -0.07424235343933105,
            -0.19305169582366943
          ],
          "hover": [
            "T[4] | 上次supporter策略: Restatement or Paraphrasing",
            "T[17] | 上次supporter策略: Restatement or Paraphrasing",
            "T[19] | 上次supporter策略: Restatement or Paraphrasing",
            "T[22] | 上次supporter策略: Restatement or Paraphrasing",
            "T[35] | 上次supporter策略: Restatement or Paraphrasing"
          ],
          "turns": [
            4,
            17,
            19,
            22,
            35
          ]
        },
        "Affirmation and Reassurance": {
          "x": [
            62.5,
            111.0,
            139.0,
            230.0,
            290.0
          ],
          "y": [
            0.028895020484924316,
            -0.15509247779846191,
            -0.07993900775909424,
            0.012168645858764648,
            -0.01361989974975586
          ],
          "hover": [
            "T[8] | 上次supporter策略: Affirmation and Reassurance",
            "T[12] | 上次supporter策略: Affirmation and Reassurance",
            "T[17] | 上次supporter策略: Affirmation and Reassurance",
            "T[26] | 上次supporter策略: Affirmation and Reassurance",
            "T[37] | 上次supporter策略: Affirmation and Reassurance"
          ],
          "turns": [
            8,
            12,
            17,
            26,
            37
          ]
        },
        "Providing Suggestions": {
          "x": [
            61.5,
            208.5,
            311.0
          ],
          "y": [
            0.028895020484924316,
            -0.12970256805419922,
            -0.06581926345825195
          ],
          "hover": [
            "T[8] | 上次supporter策略: Providing Suggestions",
            "T[24] | 上次supporter策略: Providing Suggestions",
            "T[43] | 上次supporter策略: Providing Suggestions"
          ],
          "turns": [
            8,
            24,
            43
          ]
        },
        "Information": {
          "x": [
            110.0
          ],
          "y": [
            -0.15509247779846191
          ],
          "hover": [
            "T[12] | 上次supporter策略: Information"
          ],
          "turns": [
            12
          ]
        },
        "Question": {
          "x": [
            137.0
          ],
          "y": [
            -0.07993900775909424
          ],
          "hover": [
            "T[17] | 上次supporter策略: Question"
          ],
          "turns": [
            17
          ]
        },
        "Reflection of feelings": {
          "x": [
            185.5,
            243.0
          ],
          "y": [
            -0.07424235343933105,
            0.18349993228912354
          ],
          "hover": [
            "T[22] | 上次supporter策略: Reflection of feelings",
            "T[29] | 上次supporter策略: Reflection of feelings"
          ],
          "turns": [
            22,
            29
          ]
        },
        "Others": {
          "x": [
            244.0,
            305.0,
            310.0,
            318.5
          ],
          "y": [
            0.18349993228912354,
            -0.04256713390350342,
            -0.06581926345825195,
            -0.04224503040313721
          ],
          "hover": [
            "T[29] | 上次supporter策略: Others",
            "T[40] | 上次supporter策略: Others",
            "T[43] | 上次supporter策略: Others",
            "T[45] | 上次supporter策略: Others"
          ],
          "turns": [
            29,
            40,
            43,
            45
          ]
        },
        "Self-disclosure": {
          "x": [
            264.5
          ],
          "y": [
            0.10701334476470947
          ],
          "hover": [
            "T[33] | 上次supporter策略: Self-disclosure"
          ],
          "turns": [
            33
          ]
        }
      },
      "strategy_next": {
        "Restatement or Paraphrasing": {
          "x": [
            11.5,
            124.5,
            141.0,
            165.5,
            266.5
          ],
          "y": [
            -0.012151479721069336,
            0.07459425926208496,
            -0.1897519826889038,
            -0.11200308799743652,
            -0.2294478416442871
          ],
          "hover": [
            "T[2] | 下次supporter策略: Restatement or Paraphrasing",
            "T[13] | 下次supporter策略: Restatement or Paraphrasing",
            "T[17] | 下次supporter策略: Restatement or Paraphrasing",
            "T[19] | 下次supporter策略: Restatement or Paraphrasing",
            "T[33] | 下次supporter策略: Restatement or Paraphrasing"
          ],
          "turns": [
            2,
            13,
            17,
            19,
            33
          ]
        },
        "Affirmation and Reassurance": {
          "x": [
            40.0,
            97.5,
            123.5,
            210.5,
            282.0
          ],
          "y": [
            -0.16656255722045898,
            -0.16580414772033691,
            0.07459425926208496,
            -0.07808375358581543,
            -0.0666513442993164
          ],
          "hover": [
            "T[5] | 下次supporter策略: Affirmation and Reassurance",
            "T[9] | 下次supporter策略: Affirmation and Reassurance",
            "T[13] | 下次supporter策略: Affirmation and Reassurance",
            "T[24] | 下次supporter策略: Affirmation and Reassurance",
            "T[35] | 下次supporter策略: Affirmation and Reassurance"
          ],
          "turns": [
            5,
            9,
            13,
            24,
            35
          ]
        },
        "Providing Suggestions": {
          "x": [
            41.0,
            187.5,
            307.0
          ],
          "y": [
            -0.16656255722045898,
            -0.07284021377563477,
            -0.10343790054321289
          ],
          "hover": [
            "T[5] | 下次supporter策略: Providing Suggestions",
            "T[22] | 下次supporter策略: Providing Suggestions",
            "T[40] | 下次supporter策略: Providing Suggestions"
          ],
          "turns": [
            5,
            22,
            40
          ]
        },
        "Information": {
          "x": [
            98.5
          ],
          "y": [
            -0.16580414772033691
          ],
          "hover": [
            "T[9] | 下次supporter策略: Information"
          ],
          "turns": [
            9
          ]
        },
        "Question": {
          "x": [
            125.5,
            326.0
          ],
          "y": [
            0.07459425926208496,
            0.0316011905670166
          ],
          "hover": [
            "T[13] | 下次supporter策略: Question",
            "T[46] | 下次supporter策略: Question"
          ],
          "turns": [
            13,
            46
          ]
        },
        "Reflection of feelings": {
          "x": [
            164.5,
            233.0
          ],
          "y": [
            -0.11200308799743652,
            0.14101147651672363
          ],
          "hover": [
            "T[19] | 下次supporter策略: Reflection of feelings",
            "T[26] | 下次supporter策略: Reflection of feelings"
          ],
          "turns": [
            19,
            26
          ]
        },
        "Others": {
          "x": [
            232.0,
            301.0,
            308.0,
            313.0
          ],
          "y": [
            0.14101147651672363,
            -0.018485665321350098,
            -0.10343790054321289,
            -0.020156025886535645
          ],
          "hover": [
            "T[26] | 下次supporter策略: Others",
            "T[38] | 下次supporter策略: Others",
            "T[40] | 下次supporter策略: Others",
            "T[43] | 下次supporter策略: Others"
          ],
          "turns": [
            26,
            38,
            40,
            43
          ]
        },
        "Self-disclosure": {
          "x": [
            254.0
          ],
          "y": [
            0.1147775650024414
          ],
          "hover": [
            "T[30] | 下次supporter策略: Self-disclosure"
          ],
          "turns": [
            30
          ]
        }
      }
    }
  },
  "main_context": {
    "valence": {
      "utt_x": [
        2,
        10,
        25,
        39,
        63,
        96,
        112,
        122,
        140,
        163,
        186,
        209,
        231,
        245,
        253,
        265,
        281,
        291,
        300,
        306,
        312,
        319,
        325
      ],
      "utt_y": [
        0.1303189992904663,
        -0.5565952062606812,
        -0.4373507499694824,
        -0.2778496742248535,
        -0.23896455764770508,
        -0.581514835357666,
        0.192604660987854,
        0.18888235092163086,
        -0.20118427276611328,
        0.07075643539428711,
        -0.1799328327178955,
        -0.04718518257141113,
        0.35355496406555176,
        -0.16029858589172363,
        0.050653696060180664,
        -0.06476199626922607,
        0.44395172595977783,
        0.21216249465942383,
        0.39040184020996094,
        -0.02626800537109375,
        0.2608451843261719,
        0.4054297208786011,
        0.40917229652404785
      ],
      "utt_turns": [
        1,
        2,
        4,
        5,
        8,
        9,
        12,
        13,
        17,
        19,
        22,
        24,
        26,
        29,
        30,
        33,
        35,
        37,
        38,
        40,
        43,
        45,
        46
      ],
      "ctx_x": [
        6,
        16,
        35,
        44,
        84,
        110,
        115,
        131,
        150,
        178,
        196,
        224,
        239,
        252,
        255,
        277,
        286,
        297,
        304,
        309,
        316,
        324
      ],
      "ctx_y": [
        -0.22136259078979492,
        -0.6664319634437561,
        -0.5534871220588684,
        -0.3028995990753174,
        -0.5099090337753296,
        -0.5321694612503052,
        0.16092991828918457,
        -0.13126778602600098,
        -0.14241135120391846,
        -0.06066751480102539,
        -0.10482501983642578,
        0.10250234603881836,
        0.23576664924621582,
        -0.1509239673614502,
        -0.07254481315612793,
        0.12877202033996582,
        0.4038081169128418,
        0.3467116355895996,
        0.35595619678497314,
        0.23785412311553955,
        0.2861778736114502,
        0.5042808055877686
      ],
      "ctx_turns": [
        2,
        4,
        5,
        8,
        9,
        12,
        13,
        17,
        19,
        22,
        24,
        26,
        29,
        30,
        33,
        35,
        37,
        38,
        40,
        43,
        45,
        46
      ]
    },
    "arousal": {
      "utt_x": [
        2,
        10,
        25,
        39,
        63,
        96,
        112,
        122,
        140,
        163,
        186,
        209,
        231,
        245,
        253,
        265,
        281,
        291,
        300,
        306,
        312,
        319,
        325
      ],
      "utt_y": [
        -0.015990018844604492,
        0.11302304267883301,
        0.0343172550201416,
        -0.0357666015625,
        0.04935884475708008,
        0.0785977840423584,
        0.07733535766601562,
        0.008986592292785645,
        0.050464749336242676,
        0.018169403076171875,
        -0.0360407829284668,
        -0.02083587646484375,
        0.12755918502807617,
        0.08155989646911621,
        0.10805642604827881,
        -0.040985822677612305,
        0.1538841724395752,
        0.0664207935333252,
        0.06496810913085938,
        0.1188197135925293,
        0.14809942245483398,
        0.09956037998199463,
        0.06878161430358887
      ],
      "utt_turns": [
        1,
        2,
        4,
        5,
        8,
        9,
        12,
        13,
        17,
        19,
        22,
        24,
        26,
        29,
        30,
        33,
        35,
        37,
        38,
        40,
        43,
        45,
        46
      ],
      "ctx_x": [
        6,
        16,
        35,
        44,
        84,
        110,
        115,
        131,
        150,
        178,
        196,
        224,
        239,
        252,
        255,
        277,
        286,
        297,
        304,
        309,
        316,
        324
      ],
      "ctx_y": [
        0.024518609046936035,
        0.18100571632385254,
        0.12374615669250488,
        0.049643635749816895,
        0.06666696071624756,
        0.08734512329101562,
        0.024933695793151855,
        0.025686979293823242,
        0.05579531192779541,
        0.004924893379211426,
        -0.025157928466796875,
        -0.005790114402770996,
        0.1400442123413086,
        0.070029616355896,
        -0.02537071704864502,
        0.006595969200134277,
        0.1480710506439209,
        0.0942765474319458,
        0.13886499404907227,
        0.1657170057296753,
        0.07808005809783936,
        0.15222680568695068
      ],
      "ctx_turns": [
        2,
        4,
        5,
        8,
        9,
        12,
        13,
        17,
        19,
        22,
        24,
        26,
        29,
        30,
        33,
        35,
        37,
        38,
        40,
        43,
        45,
        46
      ]
    },
    "dominance": {
      "utt_x": [
        2,
        10,
        25,
        39,
        63,
        96,
        112,
        122,
        140,
        163,
        186,
        209,
        231,
        245,
        253,
        265,
        281,
        291,
        300,
        306,
        312,
        319,
        325
      ],
      "utt_y": [
        0.02246701717376709,
        -0.16287577152252197,
        -0.1666356325149536,
        -0.15580213069915771,
        -0.008571147918701172,
        -0.1919116973876953,
        0.15478718280792236,
        0.06059598922729492,
        -0.09366416931152344,
        0.08686530590057373,
        -0.06357216835021973,
        0.002100825309753418,
        0.11076796054840088,
        0.007733583450317383,
        0.09472370147705078,
        -0.00954437255859375,
        0.08361697196960449,
        0.09586596488952637,
        0.038355231285095215,
        0.0928964614868164,
        0.09785997867584229,
        0.08475041389465332,
        -0.01929020881652832
      ],
      "utt_turns": [
        1,
        2,
        4,
        5,
        8,
        9,
        12,
        13,
        17,
        19,
        22,
        24,
        26,
        29,
        30,
        33,
        35,
        37,
        38,
        40,
        43,
        45,
        46
      ],
      "ctx_x": [
        6,
        16,
        35,
        44,
        84,
        110,
        115,
        131,
        150,
        178,
        196,
        224,
        239,
        252,
        255,
        277,
        286,
        297,
        304,
        309,
        316,
        324
      ],
      "ctx_y": [
        -0.04308724403381348,
        -0.22281360626220703,
        -0.2713124752044678,
        -0.07585489749908447,
        -0.17165184020996094,
        -0.16094017028808594,
        0.09543418884277344,
        -0.05909907817840576,
        -0.01540994644165039,
        0.022350788116455078,
        -0.034511566162109375,
        0.0557408332824707,
        0.0982292890548706,
        0.014008283615112305,
        0.006244063377380371,
        0.04264020919799805,
        0.0956716537475586,
        0.08952474594116211,
        0.06544327735900879,
        0.10306191444396973,
        0.08097290992736816,
        0.08769965171813965
      ],
      "ctx_turns": [
        2,
        4,
        5,
        8,
        9,
        12,
        13,
        17,
        19,
        22,
        24,
        26,
        29,
        30,
        33,
        35,
        37,
        38,
        40,
        43,
        45,
        46
      ]
    }
  },
  "current_sync": {
    "points": [
      [
        -0.5803312063217163,
        -0.25511860847473145,
        -0.07235968112945557
      ],
      [
        -0.5170181393623352,
        0.1512690782546997,
        -0.1918778419494629
      ],
      [
        -0.4040732979774475,
        0.09400951862335205,
        -0.24037671089172363
      ],
      [
        0.020443439483642578,
        -0.008739948272705078,
        0.028895020484924316
      ],
      [
        -0.18656599521636963,
        0.008283376693725586,
        -0.06690192222595215
      ],
      [
        -0.4379976987838745,
        0.027359843254089355,
        -0.15509247779846191
      ],
      [
        0.25510168075561523,
        -0.035051584243774414,
        0.10128188133239746
      ],
      [
        -0.16457557678222656,
        -0.07429325580596924,
        -0.07993900775909424
      ],
      [
        -0.2985039949417114,
        -0.04014003276824951,
        -0.14606285095214844
      ],
      [
        -0.16367340087890625,
        -0.02416205406188965,
        -0.07424235343933105
      ],
      [
        -0.3003067970275879,
        -0.09832906723022461,
        -0.12970256805419922
      ],
      [
        0.03232860565185547,
        0.06072962284088135,
        0.012168645858764648
      ],
      [
        0.46431398391723633,
        0.031084060668945312,
        0.18349993228912354
      ],
      [
        0.07762336730957031,
        -0.038930535316467285,
        0.09927892684936523
      ],
      [
        0.2511739730834961,
        -0.09212839603424072,
        0.10701334476470947
      ],
      [
        -0.5379452705383301,
        -0.5435932874679565,
        -0.19305169582366943
      ],
      [
        0.16574597358703613,
        0.05465054512023926,
        -0.01361989974975586
      ],
      [
        0.10864949226379395,
        0.0008560419082641602,
        -0.019766807556152344
      ],
      [
        -0.20382297039031982,
        -0.12994122505187988,
        -0.04256713390350342
      ],
      [
        -0.41151177883148193,
        -0.3251032829284668,
        -0.06581926345825195
      ],
      [
        -0.31336164474487305,
        -0.29369521141052246,
        -0.04224503040313721
      ],
      [
        -0.09525871276855469,
        -0.21954846382141113,
        -0.03551828861236572
      ]
    ],
    "turns": [
      2,
      4,
      5,
      8,
      9,
      12,
      13,
      17,
      19,
      22,
      24,
      26,
      29,
      30,
      33,
      35,
      37,
      38,
      40,
      43,
      45,
      46
    ],
    "utterance_spans": [
      10.0,
      19.0,
      9.0,
      40.0,
      26.0,
      5.0,
      16.0,
      19.0,
      28.0,
      18.0,
      28.0,
      15.0,
      13.0,
      3.0,
      22.0,
      9.0,
      11.0,
      7.0,
      5.0,
      7.0,
      8.0,
      3.0
    ]
  }
}