{
  "conv_id": 1034,
  "speaker": "seeker",
  "granularity": "sentence",
  "smooth_mode": "context",
  "window_size": 2,
  "dims": {
    "valence": {
      "is_sent": true,
      "turn_to_x": {
        "0": 0.5,
        "2": 5.5,
        "4": 19.5,
        "6": 47.5,
        "8": 70.5,
        "10": 85.0,
        "12": 108.5,
        "14": 129.5,
        "16": 137.5,
        "18": 144.5,
        "20": 160.5
      },
      "seeker_curve": {
        "x": [
          0.0,
          2.0,
          10.0,
          30.0,
          66.0,
          76.0,
          95.0,
          123.0,
          137.0,
          139.0,
          151.0
        ],
        "y": [
          0.16144275665283203,
          -0.5780901908874512,
          -0.6383465528488159,
          -0.21173226833343506,
          0.09904146194458008,
          -0.05020904541015625,
          -0.14197969436645508,
          -0.34997570514678955,
          0.026621460914611816,
          0.38553881645202637,
          0.39637112617492676
        ],
        "turns": [
          0,
          2,
          4,
          6,
          8,
          10,
          12,
          14,
          16,
          18,
          20
        ]
      },
      "prev": {
        "x": [
          5.5,
          19.5,
          47.5,
          70.5,
          85.0,
          108.5,
          129.5,
          137.5,
          144.5,
          160.5
        ],
        "y": [
          -0.5092700719833374,
          -0.6451228857040405,
          -0.19711530208587646,
          -0.1734485626220703,
          -0.16961944103240967,
          -0.3016878366470337,
          -0.056096434593200684,
          -0.42118680477142334,
          0.15637433528900146,
          0.022638440132141113
        ],
        "turns": [
          2,
          4,
          6,
          8,
          10,
          12,
          14,
          16,
          18,
          20
        ],
        "hover": [
          "T[2] ΔV=-0.509<br>上次supporter: Question<br>supporter段: T[1~1]",
          "T[4] ΔV=-0.645<br>上次supporter: Self-disclosure<br>supporter段: T[3~3]",
          "T[6] ΔV=-0.197<br>上次supporter: Restatement or Paraphrasing<br>supporter段: T[5~5]",
          "T[8] ΔV=-0.173<br>上次supporter: Self-disclosure<br>supporter段: T[7~7]",
          "T[10] ΔV=-0.170<br>上次supporter: Providing Suggestions<br>supporter段: T[9~9]",
          "T[12] ΔV=-0.302<br>上次supporter: Information<br>supporter段: T[11~11]",
          "T[14] ΔV=-0.056<br>上次supporter: Restatement or Paraphrasing<br>supporter段: T[13~13]",
          "T[16] ΔV=-0.421<br>上次supporter: Affirmation and Reassurance<br>supporter段: T[15~15]",
          "T[18] ΔV=0.156<br>上次supporter: Reflection of feelings<br>supporter段: T[17~17]",
          "T[20] ΔV=0.023<br>上次supporter: Others<br>supporter段: T[19~19]"
        ],
        "strategies": [
          [
            "Question"
          ],
          [
            "Self-disclosure"
          ],
          [
            "Restatement or Paraphrasing"
          ],
          [
            "Self-disclosure"
          ],
          [
            "Providing Suggestions"
          ],
          [
            "Information"
          ],
          [
            "Restatement or Paraphrasing"
          ],
          [
            "Affirmation and Reassurance"
          ],
          [
            "Reflection of feelings"
          ],
          [
            "Others"
          ]
        ],
        "strategy_summary": [
          "Question",
          "Self-disclosure",
          "Restatement or Paraphrasing",
          "Self-disclosure",
          "Providing Suggestions",
          "Information",
          "Restatement or Paraphrasing",
          "Affirmation and Reassurance",
          "Reflection of feelings",
          "Others"
        ]
      },
      "next": {
        "x": [
          5.5,
          19.5,
          47.5,
          70.5,
          85.0,
          108.5,
          129.5,
          137.5,
          144.5,
          160.5
        ],
        "y": [
          -0.3854069709777832,
          -0.398659348487854,
          -0.5391579866409302,
          -0.2957921028137207,
          -0.10581803321838379,
          0.019311070442199707,
          -0.371535062789917,
          -0.5056641101837158,
          -0.0385664701461792,
          -0.3236575126647949
        ],
        "turns": [
          2,
          4,
          6,
          8,
          10,
          12,
          14,
          16,
          18,
          20
        ],
        "hover": [
          "T[2] ΔV=-0.385<br>下次supporter: Self-disclosure<br>supporter段: T[3~3]",
          "T[4] ΔV=-0.399<br>下次supporter: Restatement or Paraphrasing<br>supporter段: T[5~5]",
          "T[6] ΔV=-0.539<br>下次supporter: Self-disclosure<br>supporter段: T[7~7]",
          "T[8] ΔV=-0.296<br>下次supporter: Providing Suggestions<br>supporter段: T[9~9]",
          "T[10] ΔV=-0.106<br>下次supporter: Information<br>supporter段: T[11~11]",
          "T[12] ΔV=0.019<br>下次supporter: Restatement or Paraphrasing<br>supporter段: T[13~13]",
          "T[14] ΔV=-0.372<br>下次supporter: Affirmation and Reassurance<br>supporter段: T[15~15]",
          "T[16] ΔV=-0.506<br>下次supporter: Reflection of feelings<br>supporter段: T[17~17]",
          "T[18] ΔV=-0.039<br>下次supporter: Others<br>supporter段: T[19~19]",
          "T[20] ΔV=-0.324<br>下次supporter: Others<br>supporter段: T[21~21]"
        ],
        "strategies": [
          [
            "Self-disclosure"
          ],
          [
            "Restatement or Paraphrasing"
          ],
          [
            "Self-disclosure"
          ],
          [
            "Providing Suggestions"
          ],
          [
            "Information"
          ],
          [
            "Restatement or Paraphrasing"
          ],
          [
            "Affirmation and Reassurance"
          ],
          [
            "Reflection of feelings"
          ],
          [
            "Others"
          ],
          [
            "Others"
          ]
        ],
        "strategy_summary": [
          "Self-disclosure",
          "Restatement or Paraphrasing",
          "Self-disclosure",
          "Providing Suggestions",
          "Information",
          "Restatement or Paraphrasing",
          "Affirmation and Reassurance",
          "Reflection of feelings",
          "Others",
          "Others"
        ]
      },
      "strategy_prev": {
        "Question": {
          "x": [
            4.5
          ],
          "y": [
            -0.5092700719833374
          ],
          "hover": [
            "T[2] | 上次supporter策略: Question"
          ],
          "turns": [
            2
          ]
        },
        "Self-disclosure": {
          "x": [
            18.5,
            69.5
          ],
          "y": [
            -0.6451228857040405,
            -0.1734485626220703
          ],
          "hover": [
            "T[4] | 上次supporter策略: Self-disclosure",
            "T[8] | 上次supporter策略: Self-disclosure"
          ],
          "turns": [
            4,
            8
          ]
        },
        "Restatement or Paraphrasing": {
          "x": [
            46.5,
            128.5
          ],
          "y": [
            -0.19711530208587646,
            -0.056096434593200684
          ],
          "hover": [
            "T[6] | 上次supporter策略: Restatement or Paraphrasing",
            "T[14] | 上次supporter策略: Restatement or Paraphrasing"
          ],
          "turns": [
            6,
            14
          ]
        },
        "Providing Suggestions": {
          "x": [
            84.0
          ],
          "y": [
            -0.16961944103240967
          ],
          "hover": [
            "T[10] | 上次supporter策略: Providing Suggestions"
          ],
          "turns": [
            10
          ]
        },
        "Information": {
          "x": [
            107.5
          ],
          "y": [
            -0.3016878366470337
          ],
          "hover": [
            "T[12] | 上次supporter策略: Information"
          ],
          "turns": [
            12
          ]
        },
        "Affirmation and Reassurance": {
          "x": [
            136.5
          ],
          "y": [
            -0.42118680477142334
          ],
          "hover": [
            "T[16] | 上次supporter策略: Affirmation and Reassurance"
          ],
          "turns": [
            16
          ]
        },
        "Reflection of feelings": {
          "x": [
            143.5
          ],
          "y": [
            0.15637433528900146
          ],
          "hover": [
            "T[18] | 上次supporter策略: Reflection of feelings"
          ],
          "turns": [
            18
          ]
        },
        "Others": {
          "x": [
            159.5
          ],
          "y": [
            0.022638440132141113
          ],
          "hover": [
            "T[20] | 上次supporter策略: Others"
          ],
          "turns": [
            20
          ]
        }
      },
      "strategy_next": {
        "Self-disclosure": {
          "x": [
            6.5,
            48.5
          ],
          "y": [
            -0.3854069709777832,
            -0.5391579866409302
          ],
          "hover": [
            "T[2] | 下次supporter策略: Self-disclosure",
            "T[6] | 下次supporter策略: Self-disclosure"
          ],
          "turns": [
            2,
            6
          ]
        },
        "Restatement or Paraphrasing": {
          "x": [
            20.5,
            109.5
          ],
          "y": [
            -0.398659348487854,
            0.019311070442199707
          ],
          "hover": [
            "T[4] | 下次supporter策略: Restatement or Paraphrasing",
            "T[12] | 下次supporter策略: Restatement or Paraphrasing"
          ],
          "turns": [
            4,
            12
          ]
        },
        "Providing Suggestions": {
          "x": [
            71.5
          ],
          "y": [
            -0.2957921028137207
          ],
          "hover": [
            "T[8] | 下次supporter策略: Providing Suggestions"
          ],
          "turns": [
            8
          ]
        },
        "Information": {
          "x": [
            86.0
          ],
          "y": [
            -0.10581803321838379
          ],
          "hover": [
            "T[10] | 下次supporter策略: Information"
          ],
          "turns": [
            10
          ]
        },
        "Affirmation and Reassurance": {
          "x": [
            130.5
          ],
          "y": [
            -0.371535062789917
          ],
          "hover": [
            "T[14] | 下次supporter策略: Affirmation and Reassurance"
          ],
          "turns": [
            14
          ]
        },
        "Reflection of feelings": {
          "x": [
            138.5
          ],
          "y": [
            -0.5056641101837158
          ],
          "hover": [
            "T[16] | 下次supporter策略: Reflection of feelings"
          ],
          "turns": [
            16
          ]
        },
        "Others": {
          "x": [
            145.5,
            161.5
          ],
          "y": [
            -0.0385664701461792,
            -0.3236575126647949
          ],
          "hover": [
            "T[18] | 下次supporter策略: Others",
            "T[20] | 下次supporter策略: Others"
          ],
          "turns": [
            18,
            20
          ]
        }
      }
    },
    "arousal": {
      "is_sent": true,
      "turn_to_x": {
        "0": 0.5,
        "2": 5.5,
        "4": 19.5,
        "6": 47.5,
        "8": 70.5,
        "10": 85.0,
        "12": 108.5,
        "14": 129.5,
        "16": 137.5,
        "18": 144.5,
        "20": 160.5
      },
      "seeker_curve": {
        "x": [
          0.0,
          2.0,
          10.0,
          30.0,
          66.0,
          76.0,
          95.0,
          123.0,
          137.0,
          139.0,
          151.0
        ],
        "y": [
          -0.04516589641571045,
          -0.010683894157409668,
          -0.07036185264587402,
          -0.05349445343017578,
          0.06995248794555664,
          -0.07052695751190186,
          0.015864849090576172,
          0.0748450756072998,
          -0.08216643333435059,
          0.1600358486175537,
          0.174912691116333
        ],
        "turns": [
          0,
          2,
          4,
          6,
          8,
          10,
          12,
          14,
          16,
          18,
          20
        ]
      },
      "prev": {
        "x": [
          5.5,
          19.5,
          47.5,
          70.5,
          85.0,
          108.5,
          129.5,
          137.5,
          144.5,
          160.5
        ],
        "y": [
          0.021320462226867676,
          -0.01832115650177002,
          -0.04516124725341797,
          -0.06052196025848389,
          -0.06015443801879883,
          -0.006306648254394531,
          0.0228879451751709,
          0.009033799171447754,
          0.029371261596679688,
          0.026791930198669434
        ],
        "turns": [
          2,
          4,
          6,
          8,
          10,
          12,
          14,
          16,
          18,
          20
        ],
        "hover": [
          "T[2] ΔA=0.021<br>上次supporter: Question<br>supporter段: T[1~1]",
          "T[4] ΔA=-0.018<br>上次supporter: Self-disclosure<br>supporter段: T[3~3]",
          "T[6] ΔA=-0.045<br>上次supporter: Restatement or Paraphrasing<br>supporter段: T[5~5]",
          "T[8] ΔA=-0.061<br>上次supporter: Self-disclosure<br>supporter段: T[7~7]",
          "T[10] ΔA=-0.060<br>上次supporter: Providing Suggestions<br>supporter段: T[9~9]",
          "T[12] ΔA=-0.006<br>上次supporter: Information<br>supporter段: T[11~11]",
          "T[14] ΔA=0.023<br>上次supporter: Restatement or Paraphrasing<br>supporter段: T[13~13]",
          "T[16] ΔA=0.009<br>上次supporter: Affirmation and Reassurance<br>supporter段: T[15~15]",
          "T[18] ΔA=0.029<br>上次supporter: Reflection of feelings<br>supporter段: T[17~17]",
          "T[20] ΔA=0.027<br>上次supporter: Others<br>supporter段: T[19~19]"
        ],
        "strategies": [
          [
            "Question"
          ],
          [
            "Self-disclosure"
          ],
          [
            "Restatement or Paraphrasing"
          ],
          [
            "Self-disclosure"
          ],
          [
            "Providing Suggestions"
          ],
          [
            "Information"
          ],
          [
            "Restatement or Paraphrasing"
          ],
          [
            "Affirmation and Reassurance"
          ],
          [
            "Reflection of feelings"
          ],
          [
            "Others"
          ]
        ],
        "strategy_summary": [
          "Question",
          "Self-disclosure",
          "Restatement or Paraphrasing",
          "Self-disclosure",
          "Providing Suggestions",
          "Information",
          "Restatement or Paraphrasing",
          "Affirmation and Reassurance",
          "Reflection of feelings",
          "Others"
        ]
      },
      "next": {
        "x": [
          5.5,
          19.5,
          47.5,
          70.5,
          85.0,
          108.5,
          129.5,
          137.5,
          144.5,
          160.5
        ],
        "y": [
          0.04802501201629639,
          -0.13556528091430664,
          0.014316201210021973,
          -0.10632538795471191,
          -0.002037644386291504,
          -0.045478224754333496,
          0.019371747970581055,
          -0.07187354564666748,
          -0.026177525520324707,
          -0.3137037754058838
        ],
        "turns": [
          2,
          4,
          6,
          8,
          10,
          12,
          14,
          16,
          18,
          20
        ],
        "hover": [
          "T[2] ΔA=0.048<br>下次supporter: Self-disclosure<br>supporter段: T[3~3]",
          "T[4] ΔA=-0.136<br>下次supporter: Restatement or Paraphrasing<br>supporter段: T[5~5]",
          "T[6] ΔA=0.014<br>下次supporter: Self-disclosure<br>supporter段: T[7~7]",
          "T[8] ΔA=-0.106<br>下次supporter: Providing Suggestions<br>supporter段: T[9~9]",
          "T[10] ΔA=-0.002<br>下次supporter: Information<br>supporter段: T[11~11]",
          "T[12] ΔA=-0.045<br>下次supporter: Restatement or Paraphrasing<br>supporter段: T[13~13]",
          "T[14] ΔA=0.019<br>下次supporter: Affirmation and Reassurance<br>supporter段: T[15~15]",
          "T[16] ΔA=-0.072<br>下次supporter: Reflection of feelings<br>supporter段: T[17~17]",
          "T[18] ΔA=-0.026<br>下次supporter: Others<br>supporter段: T[19~19]",
          "T[20] ΔA=-0.314<br>下次supporter: Others<br>supporter段: T[21~21]"
        ],
        "strategies": [
          [
            "Self-disclosure"
          ],
          [
            "Restatement or Paraphrasing"
          ],
          [
            "Self-disclosure"
          ],
          [
            "Providing Suggestions"
          ],
          [
            "Information"
          ],
          [
            "Restatement or Paraphrasing"
          ],
          [
            "Affirmation and Reassurance"
          ],
          [
            "Reflection of feelings"
          ],
          [
            "Others"
          ],
          [
            "Others"
          ]
        ],
        "strategy_summary": [
          "Self-disclosure",
          "Restatement or Paraphrasing",
          "Self-disclosure",
          "Providing Suggestions",
          "Information",
          "Restatement or Paraphrasing",
          "Affirmation and Reassurance",
          "Reflection of feelings",
          "Others",
          "Others"
        ]
      },
      "strategy_prev": {
        "Question": {
          "x": [
            4.5
          ],
          "y": [
            0.021320462226867676
          ],
          "hover": [
            "T[2] | 上次supporter策略: Question"
          ],
          "turns": [
            2
          ]
        },
        "Self-disclosure": {
          "x": [
            18.5,
            69.5
          ],
          "y": [
            -0.01832115650177002,
            -0.06052196025848389
          ],
          "hover": [
            "T[4] | 上次supporter策略: Self-disclosure",
            "T[8] | 上次supporter策略: Self-disclosure"
          ],
          "turns": [
            4,
            8
          ]
        },
        "Restatement or Paraphrasing": {
          "x": [
            46.5,
            128.5
          ],
          "y": [
            -0.04516124725341797,
            0.0228879451751709
          ],
          "hover": [
            "T[6] | 上次supporter策略: Restatement or Paraphrasing",
            "T[14] | 上次supporter策略: Restatement or Paraphrasing"
          ],
          "turns": [
            6,
            14
          ]
        },
        "Providing Suggestions": {
          "x": [
            84.0
          ],
          "y": [
            -0.06015443801879883
          ],
          "hover": [
            "T[10] | 上次supporter策略: Providing Suggestions"
          ],
          "turns": [
            10
          ]
        },
        "Information": {
          "x": [
            107.5
          ],
          "y": [
            -0.006306648254394531
          ],
          "hover": [
            "T[12] | 上次supporter策略: Information"
          ],
          "turns": [
            12
          ]
        },
        "Affirmation and Reassurance": {
          "x": [
            136.5
          ],
          "y": [
            0.009033799171447754
          ],
          "hover": [
            "T[16] | 上次supporter策略: Affirmation and Reassurance"
          ],
          "turns": [
            16
          ]
        },
        "Reflection of feelings": {
          "x": [
            143.5
          ],
          "y": [
            0.029371261596679688
          ],
          "hover": [
            "T[18] | 上次supporter策略: Reflection of feelings"
          ],
          "turns": [
            18
          ]
        },
        "Others": {
          "x": [
            159.5
          ],
          "y": [
            0.026791930198669434
          ],
          "hover": [
            "T[20] | 上次supporter策略: Others"
          ],
          "turns": [
            20
          ]
        }
      },
      "strategy_next": {
        "Self-disclosure": {
          "x": [
            6.5,
            48.5
          ],
          "y": [
            0.04802501201629639,
            0.014316201210021973
          ],
          "hover": [
            "T[2] | 下次supporter策略: Self-disclosure",
            "T[6] | 下次supporter策略: Self-disclosure"
          ],
          "turns": [
            2,
            6
          ]
        },
        "Restatement or Paraphrasing": {
          "x": [
            20.5,
            109.5
          ],
          "y": [
            -0.13556528091430664,
            -0.045478224754333496
          ],
          "hover": [
            "T[4] | 下次supporter策略: Restatement or Paraphrasing",
            "T[12] | 下次supporter策略: Restatement or Paraphrasing"
          ],
          "turns": [
            4,
            12
          ]
        },
        "Providing Suggestions": {
          "x": [
            71.5
          ],
          "y": [
            -0.10632538795471191
          ],
          "hover": [
            "T[8] | 下次supporter策略: Providing Suggestions"
          ],
          "turns": [
            8
          ]
        },
        "Information": {
          "x": [
            86.0
          ],
          "y": [
            -0.002037644386291504
          ],
          "hover": [
            "T[10] | 下次supporter策略: Information"
          ],
          "turns": [
            10
          ]
        },
        "Affirmation and Reassurance": {
          "x": [
            130.5
          ],
          "y": [
            0.019371747970581055
          ],
          "hover": [
            "T[14] | 下次supporter策略: Affirmation and Reassurance"
          ],
          "turns": [
            14
          ]
        },
        "Reflection of feelings": {
          "x": [
            138.5
          ],
          "y": [
            -0.07187354564666748
          ],
          "hover": [
            "T[16] | 下次supporter策略: Reflection of feelings"
          ],
          "turns": [
            16
          ]
        },
        "Others": {
          "x": [
            145.5,
            161.5
          ],
          "y": [
            -0.026177525520324707,
            -0.3137037754058838
          ],
          "hover": [
            "T[18] | 下次supporter策略: Others",
            "T[20] | 下次supporter策略: Others"
          ],
          "turns": [
            18,
            20
          ]
        }
      }
    },
    "dominance": {
      "is_sent": true,
      "turn_to_x": {
        "0": 0.5,
        "2": 5.5,
        "4": 19.5,
        "6": 47.5,
        "8": 70.5,
        "10": 85.0,
        "12": 108.5,
        "14": 129.5,
        "16": 137.5,
        "18": 144.5,
        "20": 160.5
      },
      "seeker_curve": {
        "x": [
          0.0,
          2.0,
          10.0,
          30.0,
          66.0,
          76.0,
          95.0,
          123.0,
          137.0,
          139.0,
          151.0
        ],
        "y": [
          0.012809038162231445,
          -0.30065417289733887,
          -0.3890753984451294,
          -0.10340094566345215,
          0.0742577314376831,
          0.02528202533721924,
          -0.019343137741088867,
          -0.150734543800354,
          0.07773041725158691,
          0.10351836681365967,
          0.07757329940795898
        ],
        "turns": [
          0,
          2,
          4,
          6,
          8,
          10,
          12,
          14,
          16,
          18,
          20
        ]
      },
      "prev": {
        "x": [
          5.5,
          19.5,
          47.5,
          70.5,
          85.0,
          108.5,
          129.5,
          137.5,
          144.5,
          160.5
        ],
        "y": [
          -0.18357610702514648,
          -0.4253765344619751,
          -0.14710748195648193,
          -0.11788880825042725,
          -0.008781909942626953,
          -0.12729740142822266,
          -0.05498361587524414,
          -0.20061159133911133,
          -0.04067182540893555,
          -0.018813490867614746
        ],
        "turns": [
          2,
          4,
          6,
          8,
          10,
          12,
          14,
          16,
          18,
          20
        ],
        "hover": [
          "T[2] ΔD=-0.184<br>上次supporter: Question<br>supporter段: T[1~1]",
          "T[4] ΔD=-0.425<br>上次supporter: Self-disclosure<br>supporter段: T[3~3]",
          "T[6] ΔD=-0.147<br>上次supporter: Restatement or Paraphrasing<br>supporter段: T[5~5]",
          "T[8] ΔD=-0.118<br>上次supporter: Self-disclosure<br>supporter段: T[7~7]",
          "T[10] ΔD=-0.009<br>上次supporter: Providing Suggestions<br>supporter段: T[9~9]",
          "T[12] ΔD=-0.127<br>上次supporter: Information<br>supporter段: T[11~11]",
          "T[14] ΔD=-0.055<br>上次supporter: Restatement or Paraphrasing<br>supporter段: T[13~13]",
          "T[16] ΔD=-0.201<br>上次supporter: Affirmation and Reassurance<br>supporter段: T[15~15]",
          "T[18] ΔD=-0.041<br>上次supporter: Reflection of feelings<br>supporter段: T[17~17]",
          "T[20] ΔD=-0.019<br>上次supporter: Others<br>supporter段: T[19~19]"
        ],
        "strategies": [
          [
            "Question"
          ],
          [
            "Self-disclosure"
          ],
          [
            "Restatement or Paraphrasing"
          ],
          [
            "Self-disclosure"
          ],
          [
            "Providing Suggestions"
          ],
          [
            "Information"
          ],
          [
            "Restatement or Paraphrasing"
          ],
          [
            "Affirmation and Reassurance"
          ],
          [
            "Reflection of feelings"
          ],
          [
            "Others"
          ]
        ],
        "strategy_summary": [
          "Question",
          "Self-disclosure",
          "Restatement or Paraphrasing",
          "Self-disclosure",
          "Providing Suggestions",
          "Information",
          "Restatement or Paraphrasing",
          "Affirmation and Reassurance",
          "Reflection of feelings",
          "Others"
        ]
      },
      "next": {
        "x": [
          5.5,
          19.5,
          47.5,
          70.5,
          85.0,
          108.5,
          129.5,
          137.5,
          144.5,
          160.5
        ],
        "y": [
          -0.20604801177978516,
          -0.33079075813293457,
          -0.31184065341949463,
          -0.09959101676940918,
          -0.04307675361633301,
          -0.005407094955444336,
          -0.18317079544067383,
          -0.24377036094665527,
          -0.0034373998641967773,
          -0.07824397087097168
        ],
        "turns": [
          2,
          4,
          6,
          8,
          10,
          12,
          14,
          16,
          18,
          20
        ],
        "hover": [
          "T[2] ΔD=-0.206<br>下次supporter: Self-disclosure<br>supporter段: T[3~3]",
          "T[4] ΔD=-0.331<br>下次supporter: Restatement or Paraphrasing<br>supporter段: T[5~5]",
          "T[6] ΔD=-0.312<br>下次supporter: Self-disclosure<br>supporter段: T[7~7]",
          "T[8] ΔD=-0.100<br>下次supporter: Providing Suggestions<br>supporter段: T[9~9]",
          "T[10] ΔD=-0.043<br>下次supporter: Information<br>supporter段: T[11~11]",
          "T[12] ΔD=-0.005<br>下次supporter: Restatement or Paraphrasing<br>supporter段: T[13~13]",
          "T[14] ΔD=-0.183<br>下次supporter: Affirmation and Reassurance<br>supporter段: T[15~15]",
          "T[16] ΔD=-0.244<br>下次supporter: Reflection of feelings<br>supporter段: T[17~17]",
          "T[18] ΔD=-0.003<br>下次supporter: Others<br>supporter段: T[19~19]",
          "T[20] ΔD=-0.078<br>下次supporter: Others<br>supporter段: T[21~21]"
        ],
        "strategies": [
          [
            "Self-disclosure"
          ],
          [
            "Restatement or Paraphrasing"
          ],
          [
            "Self-disclosure"
          ],
          [
            "Providing Suggestions"
          ],
          [
            "Information"
          ],
          [
            "Restatement or Paraphrasing"
          ],
          [
            "Affirmation and Reassurance"
          ],
          [
            "Reflection of feelings"
          ],
          [
            "Others"
          ],
          [
            "Others"
          ]
        ],
        "strategy_summary": [
          "Self-disclosure",
          "Restatement or Paraphrasing",
          "Self-disclosure",
          "Providing Suggestions",
          "Information",
          "Restatement or Paraphrasing",
          "Affirmation and Reassurance",
          "Reflection of feelings",
          "Others",
          "Others"
        ]
      },
      "strategy_prev": {
        "Question": {
          "x": [
            4.5
          ],
          "y": [
            -0.18357610702514648
          ],
          "hover": [
            "T[2] | 上次supporter策略: Question"
          ],
          "turns": [
            2
          ]
        },
        "Self-disclosure": {
          "x": [
            18.5,
            69.5
          ],
          "y": [
            -0.4253765344619751,
            -0.11788880825042725
          ],
          "hover": [
            "T[4] | 上次supporter策略: Self-disclosure",
            "T[8] | 上次supporter策略: Self-disclosure"
          ],
          "turns": [
            4,
            8
          ]
        },
        "Restatement or Paraphrasing": {
          "x": [
            46.5,
            128.5
          ],
          "y": [
            -0.14710748195648193,
            -0.05498361587524414
          ],
          "hover": [
            "T[6] | 上次supporter策略: Restatement or Paraphrasing",
            "T[14] | 上次supporter策略: Restatement or Paraphrasing"
          ],
          "turns": [
            6,
            14
          ]
        },
        "Providing Suggestions": {
          "x": [
            84.0
          ],
          "y": [
            -0.008781909942626953
          ],
          "hover": [
            "T[10] | 上次supporter策略: Providing Suggestions"
          ],
          "turns": [
            10
          ]
        },
        "Information": {
          "x": [
            107.5
          ],
          "y": [
            -0.12729740142822266
          ],
          "hover": [
            "T[12] | 上次supporter策略: Information"
          ],
          "turns": [
            12
          ]
        },
        "Affirmation and Reassurance": {
          "x": [
            136.5
          ],
          "y": [
            -0.20061159133911133
          ],
          "hover": [
            "T[16] | 上次supporter策略: Affirmation and Reassurance"
          ],
          "turns": [
            16
          ]
        },
        "Reflection of feelings": {
          "x": [
            143.5
          ],
          "y": [
            -0.04067182540893555
          ],
          "hover": [
            "T[18] | 上次supporter策略: Reflection of feelings"
          ],
          "turns": [
            18
          ]
        },
        "Others": {
          "x": [
            159.5
          ],
          "y": [
            -0.018813490867614746
          ],
          "hover": [
            "T[20] | 上次supporter策略: Others"
          ],
          "turns": [
            20
          ]
        }
      },
      "strategy_next": {
        "Self-disclosure": {
          "x": [
            6.5,
            48.5
          ],
          "y": [
            -0.20604801177978516,
            -0.31184065341949463
          ],
          "hover": [
            "T[2] | 下次supporter策略: Self-disclosure",
            "T[6] | 下次supporter策略: Self-disclosure"
          ],
          "turns": [
            2,
            6
          ]
        },
        "Restatement or Paraphrasing": {
          "x": [
            20.5,
            109.5
          ],
          "y": [
            -0.33079075813293457,
            -0.005407094955444336
          ],
          "hover": [
            "T[4] | 下次supporter策略: Restatement or Paraphrasing",
            "T[12] | 下次supporter策略: Restatement or Paraphrasing"
          ],
          "turns": [
            4,
            12
          ]
        },
        "Providing Suggestions": {
          "x": [
            71.5
          ],
          "y": [
            -0.09959101676940918
          ],
          "hover": [
            "T[8] | 下次supporter策略: Providing Suggestions"
          ],
          "turns": [
            8
          ]
        },
        "Information": {
          "x": [
            86.0
          ],
          "y": [
            -0.04307675361633301
          ],
          "hover": [
            "T[10] | 下次supporter策略: Information"
          ],
          "turns": [
            10
          ]
        },
        "Affirmation and Reassurance": {
          "x": [
            130.5
          ],
          "y": [
            -0.18317079544067383
          ],
          "hover": [
            "T[14] | 下次supporter策略: Affirmation and Reassurance"
          ],
          "turns": [
            14
          ]
        },
        "Reflection of feelings": {
          "x": [
            138.5
          ],
          "y": [
            -0.24377036094665527
          ],
          "hover": [
            "T[16] | 下次supporter策略: Reflection of feelings"
          ],
          "turns": [
            16
          ]
        },
        "Others": {
          "x": [
            145.5,
            161.5
          ],
          "y": [
            -0.0034373998641967773,
            -0.07824397087097168
          ],
          "hover": [
            "T[18] | 下次supporter策略: Others",
            "T[20] | 下次supporter策略: Others"
          ],
          "turns": [
            18,
            20
          ]
        }
      }
    }
  },
  "main_context": {
    "valence": {
      "utt_x": [
        0,
        5,
        19,
        47,
        70,
        85,
        108,
        129,
        137,
        144,
        160
      ],
      "utt_y": [
        0.16144275665283203,
        -0.5780901908874512,
        -0.6383465528488159,
        -0.21173226833343506,
        0.09904146194458008,
        -0.05020904541015625,
        -0.14197969436645508,
        -0.34997570514678955,
        0.026621460914611816,
        0.38553881645202637,
        0.39637112617492676
      ],
      "utt_turns": [
        0,
        2,
        4,
        6,
        8,
        10,
        12,
        14,
        16,
        18,
        20
      ],
      "ctx_x": [
        2,
        10,
        30,
        66,
        76,
        95,
        123,
        137,
        139,
        151
      ],
      "ctx_y": [
        -0.39334702491760254,
        -0.6530629396438599,
        -0.4515188932418823,
        -0.08580946922302246,
        0.040363192558288574,
        -0.15550661087036133,
        -0.23091411590576172,
        -0.28056585788726807,
        0.3814725875854492,
        0.44267749786376953
      ],
      "ctx_turns": [
        2,
        4,
        6,
        8,
        10,
        12,
        14,
        16,
        18,
        20
      ]
    },
    "arousal": {
      "utt_x": [
        0,
        5,
        19,
        47,
        70,
        85,
        108,
        129,
        137,
        144,
        160
      ],
      "utt_y": [
        -0.04516589641571045,
        -0.010683894157409668,
        -0.07036185264587402,
        -0.05349445343017578,
        0.06995248794555664,
        -0.07052695751190186,
        0.015864849090576172,
        0.0748450756072998,
        -0.08216643333435059,
        0.1600358486175537,
        0.174912691116333
      ],
      "utt_turns": [
        0,
        2,
        4,
        6,
        8,
        10,
        12,
        14,
        16,
        18,
        20
      ],
      "ctx_x": [
        2,
        10,
        30,
        66,
        76,
        95,
        123,
        137,
        139,
        151
      ],
      "ctx_y": [
        0.006887197494506836,
        -0.05945897102355957,
        0.0309450626373291,
        -0.04389309883117676,
        0.002277851104736328,
        -0.0019911527633666992,
        0.0663750171661377,
        0.056037068367004395,
        0.15728187561035156,
        0.2102513313293457
      ],
      "ctx_turns": [
        2,
        4,
        6,
        8,
        10,
        12,
        14,
        16,
        18,
        20
      ]
    },
    "dominance": {
      "utt_x": [
        0,
        5,
        19,
        47,
        70,
        85,
        108,
        129,
        137,
        144,
        160
      ],
      "utt_y": [
        0.012809038162231445,
        -0.30065417289733887,
        -0.3890753984451294,
        -0.10340094566345215,
        0.0742577314376831,
        0.02528202533721924,
        -0.019343137741088867,
        -0.150734543800354,
        0.07773041725158691,
        0.10351836681365967,
        0.07757329940795898
      ],
      "utt_turns": [
        0,
        2,
        4,
        6,
        8,
        10,
        12,
        14,
        16,
        18,
        20
      ],
      "ctx_x": [
        2,
        10,
        30,
        66,
        76,
        95,
        123,
        137,
        139,
        151
      ],
      "ctx_y": [
        -0.18457937240600586,
        -0.4039078950881958,
        -0.22022461891174316,
        -0.02627277374267578,
        0.06453633308410645,
        -0.019684314727783203,
        -0.06926083564758301,
        -0.08670163154602051,
        0.11639690399169922,
        0.10102081298828125
      ],
      "ctx_turns": [
        2,
        4,
        6,
        8,
        10,
        12,
        14,
        16,
        18,
        20
      ]
    }
  },
  "current_sync": {
    "points": [
      [
        -0.5092700719833374,
        0.021320462226867676,
        -0.18357610702514648
      ],
      [
        -0.6451228857040405,
        -0.01832115650177002,
        -0.4253765344619751
      ],
      [
        -0.19711530208587646,
        -0.04516124725341797,
        -0.14710748195648193
      ],
      [
        -0.1734485626220703,
        -0.06052196025848389,
        -0.11788880825042725
      ],
      [
        -0.16961944103240967,
        -0.06015443801879883,
        -0.008781909942626953
      ],
      [
        -0.3016878366470337,
        -0.006306648254394531,
        -0.12729740142822266
      ],
      [
        -0.056096434593200684,
        0.0228879451751709,
        -0.05498361587524414
      ],
      [
        -0.42118680477142334,
        0.009033799171447754,
        -0.20061159133911133
      ],
      [
        0.15637433528900146,
        0.029371261596679688,
        -0.04067182540893555
      ],
      [
        0.022638440132141113,
        0.026791930198669434,
        -0.018813490867614746
      ]
    ],
    "turns": [
      2,
      4,
      6,
      8,
      10,
      12,
      14,
      16,
      18,
      20
    ],
    "utterance_spans": [
      8.0,
      20.0,
      36.0,
      10.0,
      19.0,
      28.0,
      14.0,
      2.0,
      12.0,
      20.0
    ]
  }
}