{
  "metadata": {
    "conv_id": 1299,
    "speaker": "seeker",
    "granularity": "sentence"
  },
  "results": [
    {
      "term": "hi",
      "valence": 0.040522098541259766,
      "arousal": -0.08130717277526855,
      "dominance": 0.0294266939163208,
      "position": 0,
      "turn_info": {
        "turn_index": 1,
        "speaker": "seeker",
        "content": "hi",
        "strategy": null
      }
    },
    {
      "term": "i'm nereida",
      "valence": -0.026890158653259277,
      "arousal": -0.14682602882385254,
      "dominance": 7.033348083496094e-05,
      "position": 1,
      "turn_info": {
        "turn_index": 2,
        "speaker": "seeker",
        "content": "i'm nereida",
        "strategy": null
      }
    },
    {
      "term": "i am in disputed mod with my friends",
      "valence": -0.14418184757232666,
      "arousal": -0.04343366622924805,
      "dominance": -0.017964601516723633,
      "position": 2,
      "turn_info": {
        "turn_index": 4,
        "speaker": "seeker",
        "content": "i am in disputed mod with my friends",
        "strategy": null
      }
    },
    {
      "term": "I explained my personal problems but they are not ...",
      "valence": -0.532903790473938,
      "arousal": 0.07753849029541016,
      "dominance": -0.180938720703125,
      "position": 3,
      "turn_info": {
        "turn_index": 6,
        "speaker": "seeker",
        "content": "I explained my personal problems but they are not giving proper response",
        "strategy": null
      }
    },
    {
      "term": "They need more money from me, but i couldn't  give...",
      "valence": -0.294000506401062,
      "arousal": 0.03718876838684082,
      "dominance": -0.026133418083190918,
      "position": 4,
      "turn_info": {
        "turn_index": 8,
        "speaker": "seeker",
        "content": "They need more money from me, but i couldn't  give  that much amount",
        "strategy": null
      }
    },
    {
      "term": "I want to speak with them because they are in good...",
      "valence": 0.1808861494064331,
      "arousal": 0.03357529640197754,
      "dominance": 0.09937107563018799,
      "position": 5,
      "turn_info": {
        "turn_index": 10,
        "speaker": "seeker",
        "content": "I want to speak with them because they are in good nature",
        "strategy": null
      }
    },
    {
      "term": "Yes, i want to do some moderate friendship with th...",
      "valence": 0.08652687072753906,
      "arousal": -0.02053511142730713,
      "dominance": 0.08003520965576172,
      "position": 6,
      "turn_info": {
        "turn_index": 12,
        "speaker": "seeker",
        "content": "Yes, i want to do some moderate friendship with them",
        "strategy": null
      }
    },
    {
      "term": "I want to do some help to them but i don't do expe...",
      "valence": -0.07505106925964355,
      "arousal": -0.04611825942993164,
      "dominance": 0.06348299980163574,
      "position": 7,
      "turn_info": {
        "turn_index": 14,
        "speaker": "seeker",
        "content": "I want to do some help to them but i don't do expect more from them",
        "strategy": null
      }
    },
    {
      "term": "Yes, some disappointments show us about real face ...",
      "valence": -0.17434799671173096,
      "arousal": -0.019793033599853516,
      "dominance": -0.051186561584472656,
      "position": 8,
      "turn_info": {
        "turn_index": 16,
        "speaker": "seeker",
        "content": "Yes, some disappointments show us about real face of friends, so it was an experience to me.",
        "strategy": null
      }
    },
    {
      "term": "Sure, it is my new way of relationship to me with ...",
      "valence": 0.019809722900390625,
      "arousal": -0.047706007957458496,
      "dominance": 0.06198751926422119,
      "position": 9,
      "turn_info": {
        "turn_index": 18,
        "speaker": "seeker",
        "content": "Sure, it is my new way of relationship to me with others",
        "strategy": null
      }
    },
    {
      "term": "Great, thank you friend",
      "valence": 0.46115636825561523,
      "arousal": 0.1559925079345703,
      "dominance": 0.03819537162780762,
      "position": 10,
      "turn_info": {
        "turn_index": 20,
        "speaker": "seeker",
        "content": "Great, thank you friend",
        "strategy": null
      }
    }
  ]
}